  <VideoMap ShortName="EUG-ZSE" LongName="EUG-MFR-ZSE HANDOFF MAP" STARSGroup="A" STARSTDMOnly="false" VisibleInList="true" xmlns:xsi="http://www.w3.org/2001/XMLSchema-instance">
    <Colors>
      <NamedColor Red="0" Green="102" Blue="51" Name="TRACON" />
      <NamedColor Red="136" Green="137" Blue="127" Name="ZSEHO" />
    </Colors>
    <Elements>
      <Element xsi:type="Line" Color="TRACON" StartLon="0" StartLat="0" EndLon="0" EndLat="0" Style="Solid" Thickness="0" />
      <Element xsi:type="Line" Color="ZSEHO" StartLon="-122.5374972" StartLat="43.2666233" EndLon="-122.55" EndLat="43.4666667" Style="Solid" Thickness="0" />
      <Element xsi:type="Line" Color="ZSEHO" StartLon="-123.1767069" StartLat="43.3923839" EndLon="-123.1731717" EndLat="43.3923839" Style="Solid" Thickness="0" />
      <Element xsi:type="Line" Color="ZSEHO" StartLon="-123.1506342" StartLat="43.3923839" EndLon="-123.1470989" EndLat="43.3945933" Style="Solid" Thickness="0" />
      <Element xsi:type="Line" Color="ZSEHO" StartLon="-123.1731717" StartLat="43.3923839" EndLon="-123.1696364" EndLat="43.3945933" Style="Solid" Thickness="0" />
      <Element xsi:type="Line" Color="ZSEHO" StartLon="-123.2765792" StartLat="43.3923839" EndLon="-123.2730439" EndLat="43.3945933" Style="Solid" Thickness="0" />
      <Element xsi:type="Line" Color="ZSEHO" StartLon="-123.28365" StartLat="43.3923839" EndLon="-123.2765792" EndLat="43.3923839" Style="Solid" Thickness="0" />
      <Element xsi:type="Line" Color="ZSEHO" StartLon="-123.1577047" StartLat="43.3923839" EndLon="-123.1506342" EndLat="43.3923839" Style="Solid" Thickness="0" />
      <Element xsi:type="Line" Color="ZSEHO" StartLon="-123.0874406" StartLat="43.3923839" EndLon="-123.0839053" EndLat="43.3945933" Style="Solid" Thickness="0" />
      <Element xsi:type="Line" Color="ZSEHO" StartLon="-123.0945111" StartLat="43.3923839" EndLon="-123.0874406" EndLat="43.3923839" Style="Solid" Thickness="0" />
      <Element xsi:type="Line" Color="ZSEHO" StartLon="-123.1347253" StartLat="43.3923839" EndLon="-123.1347253" EndLat="43.3923839" Style="Solid" Thickness="0" />
      <Element xsi:type="Line" Color="ZSEHO" StartLon="-123.1329575" StartLat="43.3923839" EndLon="-123.1329575" EndLat="43.3945933" Style="Solid" Thickness="0" />
      <Element xsi:type="Line" Color="ZSEHO" StartLon="-123.1347253" StartLat="43.3923839" EndLon="-123.1329575" EndLat="43.3923839" Style="Solid" Thickness="0" />
      <Element xsi:type="Line" Color="ZSEHO" StartLon="-123.1802422" StartLat="43.3945933" EndLon="-123.1767069" EndLat="43.3923839" Style="Solid" Thickness="0" />
      <Element xsi:type="Line" Color="ZSEHO" StartLon="-123.1470989" StartLat="43.3945933" EndLon="-123.1470989" EndLat="43.4074089" Style="Solid" Thickness="0" />
      <Element xsi:type="Line" Color="ZSEHO" StartLon="-123.1696364" StartLat="43.3945933" EndLon="-123.1678686" EndLat="43.3972447" Style="Solid" Thickness="0" />
      <Element xsi:type="Line" Color="ZSEHO" StartLon="-123.2730439" StartLat="43.3945933" EndLon="-123.2730439" EndLat="43.4074089" Style="Solid" Thickness="0" />
      <Element xsi:type="Line" Color="ZSEHO" StartLon="-123.2871853" StartLat="43.3945933" EndLon="-123.28365" EndLat="43.3923839" Style="Solid" Thickness="0" />
      <Element xsi:type="Line" Color="ZSEHO" StartLon="-123.0839053" StartLat="43.3945933" EndLon="-123.0839053" EndLat="43.4074089" Style="Solid" Thickness="0" />
      <Element xsi:type="Line" Color="ZSEHO" StartLon="-123.0980464" StartLat="43.3945933" EndLon="-123.0945111" EndLat="43.3923839" Style="Solid" Thickness="0" />
      <Element xsi:type="Line" Color="ZSEHO" StartLon="-123.1329575" StartLat="43.3945933" EndLon="-123.1347253" EndLat="43.3945933" Style="Solid" Thickness="0" />
      <Element xsi:type="Line" Color="ZSEHO" StartLon="-123.16124" StartLat="43.3945933" EndLon="-123.1577047" EndLat="43.3923839" Style="Solid" Thickness="0" />
      <Element xsi:type="Line" Color="ZSEHO" StartLon="-123.1347253" StartLat="43.3945933" EndLon="-123.1347253" EndLat="43.3923839" Style="Solid" Thickness="0" />
      <Element xsi:type="Line" Color="ZSEHO" StartLon="-123.1678686" StartLat="43.3972447" EndLon="-123.1678686" EndLat="43.4021058" Style="Solid" Thickness="0" />
      <Element xsi:type="Line" Color="ZSEHO" StartLon="-123.18201" StartLat="43.3972447" EndLon="-123.1802422" EndLat="43.3945933" Style="Solid" Thickness="0" />
      <Element xsi:type="Line" Color="ZSEHO" StartLon="-123.23283" StartLat="43.4021058" EndLon="-123.2434358" EndLat="43.4021058" Style="Solid" Thickness="0" />
      <Element xsi:type="Line" Color="ZSEHO" StartLon="-123.1678686" StartLat="43.4021058" EndLon="-123.1696364" EndLat="43.4047572" Style="Solid" Thickness="0" />
      <Element xsi:type="Line" Color="ZSEHO" StartLon="-123.1696364" StartLat="43.4047572" EndLon="-123.1731717" EndLat="43.4074089" Style="Solid" Thickness="0" />
      <Element xsi:type="Line" Color="ZSEHO" StartLon="-123.2871853" StartLat="43.4047572" EndLon="-123.2871853" EndLat="43.4171308" Style="Solid" Thickness="0" />
      <Element xsi:type="Line" Color="ZSEHO" StartLon="-123.0980464" StartLat="43.4047572" EndLon="-123.0980464" EndLat="43.4171308" Style="Solid" Thickness="0" />
      <Element xsi:type="Line" Color="ZSEHO" StartLon="-123.16124" StartLat="43.4047572" EndLon="-123.16124" EndLat="43.4171308" Style="Solid" Thickness="0" />
      <Element xsi:type="Line" Color="ZSEHO" StartLon="-123.1767069" StartLat="43.4074089" EndLon="-123.1696364" EndLat="43.4171308" Style="Solid" Thickness="0" />
      <Element xsi:type="Line" Color="ZSEHO" StartLon="-123.1731717" StartLat="43.4074089" EndLon="-123.1767069" EndLat="43.4074089" Style="Solid" Thickness="0" />
      <Element xsi:type="Line" Color="ZSEHO" StartLon="-123.2730439" StartLat="43.4074089" EndLon="-123.2765792" EndLat="43.4074089" Style="Solid" Thickness="0" />
      <Element xsi:type="Line" Color="ZSEHO" StartLon="-123.28365" StartLat="43.4074089" EndLon="-123.2871853" EndLat="43.4047572" Style="Solid" Thickness="0" />
      <Element xsi:type="Line" Color="ZSEHO" StartLon="-123.2765792" StartLat="43.4074089" EndLon="-123.28365" EndLat="43.4074089" Style="Solid" Thickness="0" />
      <Element xsi:type="Line" Color="ZSEHO" StartLon="-123.1577047" StartLat="43.4074089" EndLon="-123.16124" EndLat="43.4047572" Style="Solid" Thickness="0" />
      <Element xsi:type="Line" Color="ZSEHO" StartLon="-123.0874406" StartLat="43.4074089" EndLon="-123.0945111" EndLat="43.4074089" Style="Solid" Thickness="0" />
      <Element xsi:type="Line" Color="ZSEHO" StartLon="-123.0839053" StartLat="43.4074089" EndLon="-123.0874406" EndLat="43.4074089" Style="Solid" Thickness="0" />
      <Element xsi:type="Line" Color="ZSEHO" StartLon="-123.0945111" StartLat="43.4074089" EndLon="-123.0980464" EndLat="43.4047572" Style="Solid" Thickness="0" />
      <Element xsi:type="Line" Color="ZSEHO" StartLon="-123.1506342" StartLat="43.4074089" EndLon="-123.1577047" EndLat="43.4074089" Style="Solid" Thickness="0" />
      <Element xsi:type="Line" Color="ZSEHO" StartLon="-123.1470989" StartLat="43.4074089" EndLon="-123.1506342" EndLat="43.4074089" Style="Solid" Thickness="0" />
      <Element xsi:type="Line" Color="ZSEHO" StartLon="-122.2981839" StartLat="43.4082928" EndLon="-122.2981839" EndLat="43.4109442" Style="Solid" Thickness="0" />
      <Element xsi:type="Line" Color="ZSEHO" StartLon="-122.3419333" StartLat="43.4082928" EndLon="-122.3383981" EndLat="43.4082928" Style="Solid" Thickness="0" />
      <Element xsi:type="Line" Color="ZSEHO" StartLon="-122.3383981" StartLat="43.4082928" EndLon="-122.3348628" EndLat="43.4109442" Style="Solid" Thickness="0" />
      <Element xsi:type="Line" Color="ZSEHO" StartLon="-122.2999517" StartLat="43.4082928" EndLon="-122.2981839" EndLat="43.4082928" Style="Solid" Thickness="0" />
      <Element xsi:type="Line" Color="ZSEHO" StartLon="-122.2738786" StartLat="43.4082928" EndLon="-122.2809494" EndLat="43.4082928" Style="Solid" Thickness="0" />
      <Element xsi:type="Line" Color="ZSEHO" StartLon="-122.2809494" StartLat="43.4082928" EndLon="-122.2844847" EndLat="43.4109442" Style="Solid" Thickness="0" />
      <Element xsi:type="Line" Color="ZSEHO" StartLon="-122.2999517" StartLat="43.4082928" EndLon="-122.2999517" EndLat="43.4082928" Style="Solid" Thickness="0" />
      <Element xsi:type="Line" Color="ZSEHO" StartLon="-123.3061875" StartLat="43.4096183" EndLon="-123.3008844" EndLat="43.4171308" Style="Solid" Thickness="0" />
      <Element xsi:type="Line" Color="ZSEHO" StartLon="-123.2014542" StartLat="43.4096183" EndLon="-123.1961511" EndLat="43.4171308" Style="Solid" Thickness="0" />
      <Element xsi:type="Line" Color="ZSEHO" StartLon="-123.1174906" StartLat="43.4096183" EndLon="-123.1121878" EndLat="43.4171308" Style="Solid" Thickness="0" />
      <Element xsi:type="Line" Color="ZSEHO" StartLon="-122.3454686" StartLat="43.4109442" EndLon="-122.3419333" EndLat="43.4082928" Style="Solid" Thickness="0" />
      <Element xsi:type="Line" Color="ZSEHO" StartLon="-122.3348628" StartLat="43.4109442" EndLon="-122.333095" EndLat="43.4131536" Style="Solid" Thickness="0" />
      <Element xsi:type="Line" Color="ZSEHO" StartLon="-122.2981839" StartLat="43.4109442" EndLon="-122.2999517" EndLat="43.4109442" Style="Solid" Thickness="0" />
      <Element xsi:type="Line" Color="ZSEHO" StartLon="-122.2999517" StartLat="43.4109442" EndLon="-122.2999517" EndLat="43.4082928" Style="Solid" Thickness="0" />
      <Element xsi:type="Line" Color="ZSEHO" StartLon="-122.333095" StartLat="43.4131536" EndLon="-122.333095" EndLat="43.4184567" Style="Solid" Thickness="0" />
      <Element xsi:type="Line" Color="ZSEHO" StartLon="-122.3472364" StartLat="43.4131536" EndLon="-122.3454686" EndLat="43.4109442" Style="Solid" Thickness="0" />
      <Element xsi:type="Line" Color="ZSEHO" StartLon="-122.2703433" StartLat="43.4131536" EndLon="-122.2738786" EndLat="43.4082928" Style="Solid" Thickness="0" />
      <Element xsi:type="Line" Color="ZSEHO" StartLon="-122.4382703" StartLat="43.4158053" EndLon="-122.4524117" EndLat="43.4158053" Style="Solid" Thickness="0" />
      <Element xsi:type="Line" Color="ZSEHO" StartLon="-122.4524117" StartLat="43.4158053" EndLon="-122.4435733" EndLat="43.4334817" Style="Solid" Thickness="0" />
      <Element xsi:type="Line" Color="ZSEHO" StartLon="-122.3123253" StartLat="43.4158053" EndLon="-122.3264664" EndLat="43.4158053" Style="Solid" Thickness="0" />
      <Element xsi:type="Line" Color="ZSEHO" StartLon="-122.3264664" StartLat="43.4158053" EndLon="-122.3176281" EndLat="43.4334817" Style="Solid" Thickness="0" />
      <Element xsi:type="Line" Color="ZSEHO" StartLon="-123.1961511" StartLat="43.4171308" EndLon="-123.1961511" EndLat="43.3923839" Style="Solid" Thickness="0" />
      <Element xsi:type="Line" Color="ZSEHO" StartLon="-123.2871853" StartLat="43.4171308" EndLon="-123.2730439" EndLat="43.4171308" Style="Solid" Thickness="0" />
      <Element xsi:type="Line" Color="ZSEHO" StartLon="-123.3008844" StartLat="43.4171308" EndLon="-123.3008844" EndLat="43.3923839" Style="Solid" Thickness="0" />
      <Element xsi:type="Line" Color="ZSEHO" StartLon="-123.1696364" StartLat="43.4171308" EndLon="-123.1802422" EndLat="43.4171308" Style="Solid" Thickness="0" />
      <Element xsi:type="Line" Color="ZSEHO" StartLon="-123.0980464" StartLat="43.4171308" EndLon="-123.0839053" EndLat="43.4171308" Style="Solid" Thickness="0" />
      <Element xsi:type="Line" Color="ZSEHO" StartLon="-123.1121878" StartLat="43.4171308" EndLon="-123.1121878" EndLat="43.3923839" Style="Solid" Thickness="0" />
      <Element xsi:type="Line" Color="ZSEHO" StartLon="-123.16124" StartLat="43.4171308" EndLon="-123.1470989" EndLat="43.4171308" Style="Solid" Thickness="0" />
      <Element xsi:type="Line" Color="ZSEHO" StartLon="-122.333095" StartLat="43.4184567" EndLon="-122.3348628" EndLat="43.4206661" Style="Solid" Thickness="0" />
      <Element xsi:type="Line" Color="ZSEHO" StartLon="-122.3980564" StartLat="43.4184567" EndLon="-122.4086622" EndLat="43.4184567" Style="Solid" Thickness="0" />
      <Element xsi:type="Line" Color="ZSEHO" StartLon="-122.2738786" StartLat="43.4184567" EndLon="-122.2809494" EndLat="43.4184567" Style="Solid" Thickness="0" />
      <Element xsi:type="Line" Color="ZSEHO" StartLon="-122.2809494" StartLat="43.4184567" EndLon="-122.2844847" EndLat="43.4233178" Style="Solid" Thickness="0" />
      <Element xsi:type="Line" Color="ZSEHO" StartLon="-122.3348628" StartLat="43.4206661" EndLon="-122.3383981" EndLat="43.4233178" Style="Solid" Thickness="0" />
      <Element xsi:type="Line" Color="ZSEHO" StartLon="-122.3383981" StartLat="43.4233178" EndLon="-122.3419333" EndLat="43.4233178" Style="Solid" Thickness="0" />
      <Element xsi:type="Line" Color="ZSEHO" StartLon="-122.3419333" StartLat="43.4233178" EndLon="-122.3348628" EndLat="43.4334817" Style="Solid" Thickness="0" />
      <Element xsi:type="Line" Color="ZSEHO" StartLon="-122.2703433" StartLat="43.4233178" EndLon="-122.2738786" EndLat="43.4184567" Style="Solid" Thickness="0" />
      <Element xsi:type="Line" Color="ZSEHO" StartLon="-122.2844847" StartLat="43.4233178" EndLon="-122.2844847" EndLat="43.4281789" Style="Solid" Thickness="0" />
      <Element xsi:type="Line" Color="ZSEHO" StartLon="-122.4714139" StartLat="43.4259692" EndLon="-122.4661108" EndLat="43.4334817" Style="Solid" Thickness="0" />
      <Element xsi:type="Line" Color="ZSEHO" StartLon="-122.3666806" StartLat="43.4259692" EndLon="-122.3613775" EndLat="43.4334817" Style="Solid" Thickness="0" />
      <Element xsi:type="Line" Color="ZSEHO" StartLon="-122.2703433" StartLat="43.4281789" EndLon="-122.2703433" EndLat="43.4131536" Style="Solid" Thickness="0" />
      <Element xsi:type="Line" Color="ZSEHO" StartLon="-122.2844847" StartLat="43.4281789" EndLon="-122.2809494" EndLat="43.4334817" Style="Solid" Thickness="0" />
      <Element xsi:type="Line" Color="ZSEHO" StartLon="-122.3613775" StartLat="43.4334817" EndLon="-122.3613775" EndLat="43.4082928" Style="Solid" Thickness="0" />
      <Element xsi:type="Line" Color="ZSEHO" StartLon="-122.4435733" StartLat="43.4334817" EndLon="-122.4435733" EndLat="43.4082928" Style="Solid" Thickness="0" />
      <Element xsi:type="Line" Color="ZSEHO" StartLon="-122.4661108" StartLat="43.4334817" EndLon="-122.4661108" EndLat="43.4082928" Style="Solid" Thickness="0" />
      <Element xsi:type="Line" Color="ZSEHO" StartLon="-122.3348628" StartLat="43.4334817" EndLon="-122.3454686" EndLat="43.4334817" Style="Solid" Thickness="0" />
      <Element xsi:type="Line" Color="ZSEHO" StartLon="-122.2809494" StartLat="43.4334817" EndLon="-122.2738786" EndLat="43.4334817" Style="Solid" Thickness="0" />
      <Element xsi:type="Line" Color="ZSEHO" StartLon="-122.2738786" StartLat="43.4334817" EndLon="-122.2703433" EndLat="43.4281789" Style="Solid" Thickness="0" />
      <Element xsi:type="Line" Color="ZSEHO" StartLon="-122.3176281" StartLat="43.4334817" EndLon="-122.3176281" EndLat="43.4082928" Style="Solid" Thickness="0" />
      <Element xsi:type="Line" Color="ZSEHO" StartLon="-122.9666667" StartLat="43.4666667" EndLon="-124.6083333" EndLat="43.8833333" Style="Solid" Thickness="0" />
      <Element xsi:type="Line" Color="ZSEHO" StartLon="-122.55" StartLat="43.4666667" EndLon="-122.9666667" EndLat="43.4666667" Style="Solid" Thickness="0" />
      <Element xsi:type="Line" Color="ZSEHO" StartLon="-122.5527258" StartLat="43.6482514" EndLon="-122.5456553" EndLat="43.6482514" Style="Solid" Thickness="0" />
      <Element xsi:type="Line" Color="ZSEHO" StartLon="-122.4510858" StartLat="43.6482514" EndLon="-122.4510858" EndLat="43.6531125" Style="Solid" Thickness="0" />
      <Element xsi:type="Line" Color="ZSEHO" StartLon="-122.4369447" StartLat="43.6482514" EndLon="-122.4510858" EndLat="43.6482514" Style="Solid" Thickness="0" />
      <Element xsi:type="Line" Color="ZSEHO" StartLon="-122.5681928" StartLat="43.6482514" EndLon="-122.5646575" EndLat="43.6504611" Style="Solid" Thickness="0" />
      <Element xsi:type="Line" Color="ZSEHO" StartLon="-122.5717281" StartLat="43.6482514" EndLon="-122.5681928" EndLat="43.6482514" Style="Solid" Thickness="0" />
      <Element xsi:type="Line" Color="ZSEHO" StartLon="-122.5456553" StartLat="43.6482514" EndLon="-122.54212" EndLat="43.6531125" Style="Solid" Thickness="0" />
      <Element xsi:type="Line" Color="ZSEHO" StartLon="-122.41971" StartLat="43.6482514" EndLon="-122.4161747" EndLat="43.6504611" Style="Solid" Thickness="0" />
      <Element xsi:type="Line" Color="ZSEHO" StartLon="-122.4038011" StartLat="43.6482514" EndLon="-122.4038011" EndLat="43.6482514" Style="Solid" Thickness="0" />
      <Element xsi:type="Line" Color="ZSEHO" StartLon="-122.3777283" StartLat="43.6482514" EndLon="-122.3741931" EndLat="43.6531125" Style="Solid" Thickness="0" />
      <Element xsi:type="Line" Color="ZSEHO" StartLon="-122.3847989" StartLat="43.6482514" EndLon="-122.3777283" EndLat="43.6482514" Style="Solid" Thickness="0" />
      <Element xsi:type="Line" Color="ZSEHO" StartLon="-122.4267806" StartLat="43.6482514" EndLon="-122.41971" EndLat="43.6482514" Style="Solid" Thickness="0" />
      <Element xsi:type="Line" Color="ZSEHO" StartLon="-122.4020336" StartLat="43.6482514" EndLon="-122.4020336" EndLat="43.6504611" Style="Solid" Thickness="0" />
      <Element xsi:type="Line" Color="ZSEHO" StartLon="-122.4038011" StartLat="43.6482514" EndLon="-122.4020336" EndLat="43.6482514" Style="Solid" Thickness="0" />
      <Element xsi:type="Line" Color="ZSEHO" StartLon="-122.5752633" StartLat="43.6504611" EndLon="-122.5752633" EndLat="43.6504611" Style="Solid" Thickness="0" />
      <Element xsi:type="Line" Color="ZSEHO" StartLon="-122.5752633" StartLat="43.6504611" EndLon="-122.5717281" EndLat="43.6482514" Style="Solid" Thickness="0" />
      <Element xsi:type="Line" Color="ZSEHO" StartLon="-122.5646575" StartLat="43.6504611" EndLon="-122.5628897" EndLat="43.6557639" Style="Solid" Thickness="0" />
      <Element xsi:type="Line" Color="ZSEHO" StartLon="-122.4161747" StartLat="43.6504611" EndLon="-122.4161747" EndLat="43.6632764" Style="Solid" Thickness="0" />
      <Element xsi:type="Line" Color="ZSEHO" StartLon="-122.4020336" StartLat="43.6504611" EndLon="-122.4038011" EndLat="43.6504611" Style="Solid" Thickness="0" />
      <Element xsi:type="Line" Color="ZSEHO" StartLon="-122.4038011" StartLat="43.6504611" EndLon="-122.4038011" EndLat="43.6482514" Style="Solid" Thickness="0" />
      <Element xsi:type="Line" Color="ZSEHO" StartLon="-122.4298739" StartLat="43.6504611" EndLon="-122.4267806" EndLat="43.6482514" Style="Solid" Thickness="0" />
      <Element xsi:type="Line" Color="ZSEHO" StartLon="-122.5558192" StartLat="43.6531125" EndLon="-122.5527258" EndLat="43.6482514" Style="Solid" Thickness="0" />
      <Element xsi:type="Line" Color="ZSEHO" StartLon="-122.54212" StartLat="43.6531125" EndLon="-122.54212" EndLat="43.6579736" Style="Solid" Thickness="0" />
      <Element xsi:type="Line" Color="ZSEHO" StartLon="-122.4510858" StartLat="43.6531125" EndLon="-122.4369447" EndLat="43.6654861" Style="Solid" Thickness="0" />
      <Element xsi:type="Line" Color="ZSEHO" StartLon="-122.3878922" StartLat="43.6531125" EndLon="-122.3847989" EndLat="43.6482514" Style="Solid" Thickness="0" />
      <Element xsi:type="Line" Color="ZSEHO" StartLon="-122.3741931" StartLat="43.6531125" EndLon="-122.3741931" EndLat="43.6557639" Style="Solid" Thickness="0" />
      <Element xsi:type="Line" Color="ZSEHO" StartLon="-122.5628897" StartLat="43.6557639" EndLon="-122.5628897" EndLat="43.6654861" Style="Solid" Thickness="0" />
      <Element xsi:type="Line" Color="ZSEHO" StartLon="-122.5770311" StartLat="43.6557639" EndLon="-122.5752633" EndLat="43.6504611" Style="Solid" Thickness="0" />
      <Element xsi:type="Line" Color="ZSEHO" StartLon="-122.3878922" StartLat="43.6557639" EndLon="-122.3878922" EndLat="43.6531125" Style="Solid" Thickness="0" />
      <Element xsi:type="Line" Color="ZSEHO" StartLon="-122.3741931" StartLat="43.6557639" EndLon="-122.3794958" EndLat="43.660625" Style="Solid" Thickness="0" />
      <Element xsi:type="Line" Color="ZSEHO" StartLon="-122.54212" StartLat="43.6579736" EndLon="-122.5456553" EndLat="43.6632764" Style="Solid" Thickness="0" />
      <Element xsi:type="Line" Color="ZSEHO" StartLon="-122.5019058" StartLat="43.6579736" EndLon="-122.5125117" EndLat="43.6579736" Style="Solid" Thickness="0" />
      <Element xsi:type="Line" Color="ZSEHO" StartLon="-122.3794958" StartLat="43.660625" EndLon="-122.3830311" EndLat="43.660625" Style="Solid" Thickness="0" />
      <Element xsi:type="Line" Color="ZSEHO" StartLon="-122.4298739" StartLat="43.660625" EndLon="-122.4298739" EndLat="43.6729986" Style="Solid" Thickness="0" />
      <Element xsi:type="Line" Color="ZSEHO" StartLon="-122.3794958" StartLat="43.660625" EndLon="-122.3741931" EndLat="43.6654861" Style="Solid" Thickness="0" />
      <Element xsi:type="Line" Color="ZSEHO" StartLon="-122.3830311" StartLat="43.660625" EndLon="-122.3878922" EndLat="43.6557639" Style="Solid" Thickness="0" />
      <Element xsi:type="Line" Color="ZSEHO" StartLon="-122.5456553" StartLat="43.6632764" EndLon="-122.5527258" EndLat="43.6632764" Style="Solid" Thickness="0" />
      <Element xsi:type="Line" Color="ZSEHO" StartLon="-122.5527258" StartLat="43.6632764" EndLon="-122.5558192" EndLat="43.6579736" Style="Solid" Thickness="0" />
      <Element xsi:type="Line" Color="ZSEHO" StartLon="-122.4267806" StartLat="43.6632764" EndLon="-122.4298739" EndLat="43.660625" Style="Solid" Thickness="0" />
      <Element xsi:type="Line" Color="ZSEHO" StartLon="-122.4161747" StartLat="43.6632764" EndLon="-122.41971" EndLat="43.6632764" Style="Solid" Thickness="0" />
      <Element xsi:type="Line" Color="ZSEHO" StartLon="-122.41971" StartLat="43.6632764" EndLon="-122.4267806" EndLat="43.6632764" Style="Solid" Thickness="0" />
      <Element xsi:type="Line" Color="ZSEHO" StartLon="-122.47053" StartLat="43.6654861" EndLon="-122.4652269" EndLat="43.6729986" Style="Solid" Thickness="0" />
      <Element xsi:type="Line" Color="ZSEHO" StartLon="-122.5628897" StartLat="43.6654861" EndLon="-122.5646575" EndLat="43.6707889" Style="Solid" Thickness="0" />
      <Element xsi:type="Line" Color="ZSEHO" StartLon="-122.5770311" StartLat="43.6654861" EndLon="-122.5770311" EndLat="43.6557639" Style="Solid" Thickness="0" />
      <Element xsi:type="Line" Color="ZSEHO" StartLon="-122.3741931" StartLat="43.6654861" EndLon="-122.3741931" EndLat="43.6681375" Style="Solid" Thickness="0" />
      <Element xsi:type="Line" Color="ZSEHO" StartLon="-122.3878922" StartLat="43.6654861" EndLon="-122.3830311" EndLat="43.660625" Style="Solid" Thickness="0" />
      <Element xsi:type="Line" Color="ZSEHO" StartLon="-122.4369447" StartLat="43.6654861" EndLon="-122.4369447" EndLat="43.6707889" Style="Solid" Thickness="0" />
      <Element xsi:type="Line" Color="ZSEHO" StartLon="-122.5558192" StartLat="43.6681375" EndLon="-122.5558192" EndLat="43.6531125" Style="Solid" Thickness="0" />
      <Element xsi:type="Line" Color="ZSEHO" StartLon="-122.3878922" StartLat="43.6681375" EndLon="-122.3878922" EndLat="43.6654861" Style="Solid" Thickness="0" />
      <Element xsi:type="Line" Color="ZSEHO" StartLon="-122.3741931" StartLat="43.6681375" EndLon="-122.3777283" EndLat="43.6729986" Style="Solid" Thickness="0" />
      <Element xsi:type="Line" Color="ZSEHO" StartLon="-122.5646575" StartLat="43.6707889" EndLon="-122.5681928" EndLat="43.6729986" Style="Solid" Thickness="0" />
      <Element xsi:type="Line" Color="ZSEHO" StartLon="-122.5752633" StartLat="43.6707889" EndLon="-122.5770311" EndLat="43.6654861" Style="Solid" Thickness="0" />
      <Element xsi:type="Line" Color="ZSEHO" StartLon="-122.4369447" StartLat="43.6707889" EndLon="-122.44048" EndLat="43.6729986" Style="Solid" Thickness="0" />
      <Element xsi:type="Line" Color="ZSEHO" StartLon="-122.54212" StartLat="43.6707889" EndLon="-122.5456553" EndLat="43.6729986" Style="Solid" Thickness="0" />
      <Element xsi:type="Line" Color="ZSEHO" StartLon="-122.5456553" StartLat="43.6729986" EndLon="-122.5527258" EndLat="43.6729986" Style="Solid" Thickness="0" />
      <Element xsi:type="Line" Color="ZSEHO" StartLon="-122.4652269" StartLat="43.6729986" EndLon="-122.4652269" EndLat="43.6482514" Style="Solid" Thickness="0" />
      <Element xsi:type="Line" Color="ZSEHO" StartLon="-122.5527258" StartLat="43.6729986" EndLon="-122.5558192" EndLat="43.6681375" Style="Solid" Thickness="0" />
      <Element xsi:type="Line" Color="ZSEHO" StartLon="-122.5717281" StartLat="43.6729986" EndLon="-122.5752633" EndLat="43.6707889" Style="Solid" Thickness="0" />
      <Element xsi:type="Line" Color="ZSEHO" StartLon="-122.5681928" StartLat="43.6729986" EndLon="-122.5717281" EndLat="43.6729986" Style="Solid" Thickness="0" />
      <Element xsi:type="Line" Color="ZSEHO" StartLon="-122.3847989" StartLat="43.6729986" EndLon="-122.3878922" EndLat="43.6681375" Style="Solid" Thickness="0" />
      <Element xsi:type="Line" Color="ZSEHO" StartLon="-122.3777283" StartLat="43.6729986" EndLon="-122.3847989" EndLat="43.6729986" Style="Solid" Thickness="0" />
      <Element xsi:type="Line" Color="ZSEHO" StartLon="-122.4298739" StartLat="43.6729986" EndLon="-122.4161747" EndLat="43.6729986" Style="Solid" Thickness="0" />
      <Element xsi:type="Line" Color="ZSEHO" StartLon="-122.4475506" StartLat="43.6729986" EndLon="-122.4510858" EndLat="43.6707889" Style="Solid" Thickness="0" />
      <Element xsi:type="Line" Color="ZSEHO" StartLon="-122.44048" StartLat="43.6729986" EndLon="-122.4475506" EndLat="43.6729986" Style="Solid" Thickness="0" />
      <Element xsi:type="Line" Color="ZSEHO" StartLon="-122.1603558" StartLat="43.6953708" EndLon="-122.55" EndLat="43.4666667" Style="Solid" Thickness="0" />
      <Element xsi:type="Line" Color="ZSEHO" StartLon="-124.4273208" StartLat="43.7087936" EndLon="-124.4237853" EndLat="43.7087936" Style="Solid" Thickness="0" />
      <Element xsi:type="Line" Color="ZSEHO" StartLon="-124.4012478" StartLat="43.7087936" EndLon="-124.3977125" EndLat="43.711445" Style="Solid" Thickness="0" />
      <Element xsi:type="Line" Color="ZSEHO" StartLon="-124.4237853" StartLat="43.7087936" EndLon="-124.42025" EndLat="43.711445" Style="Solid" Thickness="0" />
      <Element xsi:type="Line" Color="ZSEHO" StartLon="-124.5271931" StartLat="43.7087936" EndLon="-124.5236578" EndLat="43.711445" Style="Solid" Thickness="0" />
      <Element xsi:type="Line" Color="ZSEHO" StartLon="-124.5338217" StartLat="43.7087936" EndLon="-124.5271931" EndLat="43.7087936" Style="Solid" Thickness="0" />
      <Element xsi:type="Line" Color="ZSEHO" StartLon="-124.4078767" StartLat="43.7087936" EndLon="-124.4012478" EndLat="43.7087936" Style="Solid" Thickness="0" />
      <Element xsi:type="Line" Color="ZSEHO" StartLon="-124.3380542" StartLat="43.7087936" EndLon="-124.3345189" EndLat="43.711445" Style="Solid" Thickness="0" />
      <Element xsi:type="Line" Color="ZSEHO" StartLon="-124.345125" StartLat="43.7087936" EndLon="-124.3380542" EndLat="43.7087936" Style="Solid" Thickness="0" />
      <Element xsi:type="Line" Color="ZSEHO" StartLon="-124.3853389" StartLat="43.7087936" EndLon="-124.3853389" EndLat="43.7087936" Style="Solid" Thickness="0" />
      <Element xsi:type="Line" Color="ZSEHO" StartLon="-124.3835714" StartLat="43.7087936" EndLon="-124.3835714" EndLat="43.711445" Style="Solid" Thickness="0" />
      <Element xsi:type="Line" Color="ZSEHO" StartLon="-124.3853389" StartLat="43.7087936" EndLon="-124.3835714" EndLat="43.7087936" Style="Solid" Thickness="0" />
      <Element xsi:type="Line" Color="ZSEHO" StartLon="-124.4308561" StartLat="43.711445" EndLon="-124.4273208" EndLat="43.7087936" Style="Solid" Thickness="0" />
      <Element xsi:type="Line" Color="ZSEHO" StartLon="-124.3977125" StartLat="43.711445" EndLon="-124.3977125" EndLat="43.7238186" Style="Solid" Thickness="0" />
      <Element xsi:type="Line" Color="ZSEHO" StartLon="-124.42025" StartLat="43.711445" EndLon="-124.4184825" EndLat="43.7140964" Style="Solid" Thickness="0" />
      <Element xsi:type="Line" Color="ZSEHO" StartLon="-124.5236578" StartLat="43.711445" EndLon="-124.5236578" EndLat="43.7238186" Style="Solid" Thickness="0" />
      <Element xsi:type="Line" Color="ZSEHO" StartLon="-124.5373569" StartLat="43.711445" EndLon="-124.5338217" EndLat="43.7087936" Style="Solid" Thickness="0" />
      <Element xsi:type="Line" Color="ZSEHO" StartLon="-124.3345189" StartLat="43.711445" EndLon="-124.3345189" EndLat="43.7238186" Style="Solid" Thickness="0" />
      <Element xsi:type="Line" Color="ZSEHO" StartLon="-124.3486603" StartLat="43.711445" EndLon="-124.345125" EndLat="43.7087936" Style="Solid" Thickness="0" />
      <Element xsi:type="Line" Color="ZSEHO" StartLon="-124.3835714" StartLat="43.711445" EndLon="-124.3853389" EndLat="43.711445" Style="Solid" Thickness="0" />
      <Element xsi:type="Line" Color="ZSEHO" StartLon="-124.4114119" StartLat="43.711445" EndLon="-124.4078767" EndLat="43.7087936" Style="Solid" Thickness="0" />
      <Element xsi:type="Line" Color="ZSEHO" StartLon="-124.3853389" StartLat="43.711445" EndLon="-124.3853389" EndLat="43.7087936" Style="Solid" Thickness="0" />
      <Element xsi:type="Line" Color="ZSEHO" StartLon="-124.4184825" StartLat="43.7140964" EndLon="-124.4184825" EndLat="43.7189575" Style="Solid" Thickness="0" />
      <Element xsi:type="Line" Color="ZSEHO" StartLon="-124.4326236" StartLat="43.7140964" EndLon="-124.4308561" EndLat="43.711445" Style="Solid" Thickness="0" />
      <Element xsi:type="Line" Color="ZSEHO" StartLon="-124.4834436" StartLat="43.7189575" EndLon="-124.4936078" EndLat="43.7189575" Style="Solid" Thickness="0" />
      <Element xsi:type="Line" Color="ZSEHO" StartLon="-124.4184825" StartLat="43.7189575" EndLon="-124.42025" EndLat="43.7216089" Style="Solid" Thickness="0" />
      <Element xsi:type="Line" Color="ZSEHO" StartLon="-124.42025" StartLat="43.7216089" EndLon="-124.4237853" EndLat="43.7238186" Style="Solid" Thickness="0" />
      <Element xsi:type="Line" Color="ZSEHO" StartLon="-124.5373569" StartLat="43.7216089" EndLon="-124.5373569" EndLat="43.7339825" Style="Solid" Thickness="0" />
      <Element xsi:type="Line" Color="ZSEHO" StartLon="-124.3486603" StartLat="43.7216089" EndLon="-124.3486603" EndLat="43.7339825" Style="Solid" Thickness="0" />
      <Element xsi:type="Line" Color="ZSEHO" StartLon="-124.4114119" StartLat="43.7216089" EndLon="-124.4114119" EndLat="43.7339825" Style="Solid" Thickness="0" />
      <Element xsi:type="Line" Color="ZSEHO" StartLon="-124.4273208" StartLat="43.7238186" EndLon="-124.42025" EndLat="43.7339825" Style="Solid" Thickness="0" />
      <Element xsi:type="Line" Color="ZSEHO" StartLon="-124.4237853" StartLat="43.7238186" EndLon="-124.4273208" EndLat="43.7238186" Style="Solid" Thickness="0" />
      <Element xsi:type="Line" Color="ZSEHO" StartLon="-124.5236578" StartLat="43.7238186" EndLon="-124.5271931" EndLat="43.7238186" Style="Solid" Thickness="0" />
      <Element xsi:type="Line" Color="ZSEHO" StartLon="-124.5338217" StartLat="43.7238186" EndLon="-124.5373569" EndLat="43.7216089" Style="Solid" Thickness="0" />
      <Element xsi:type="Line" Color="ZSEHO" StartLon="-124.5271931" StartLat="43.7238186" EndLon="-124.5338217" EndLat="43.7238186" Style="Solid" Thickness="0" />
      <Element xsi:type="Line" Color="ZSEHO" StartLon="-124.4078767" StartLat="43.7238186" EndLon="-124.4114119" EndLat="43.7216089" Style="Solid" Thickness="0" />
      <Element xsi:type="Line" Color="ZSEHO" StartLon="-124.3380542" StartLat="43.7238186" EndLon="-124.345125" EndLat="43.7238186" Style="Solid" Thickness="0" />
      <Element xsi:type="Line" Color="ZSEHO" StartLon="-124.3345189" StartLat="43.7238186" EndLon="-124.3380542" EndLat="43.7238186" Style="Solid" Thickness="0" />
      <Element xsi:type="Line" Color="ZSEHO" StartLon="-124.345125" StartLat="43.7238186" EndLon="-124.3486603" EndLat="43.7216089" Style="Solid" Thickness="0" />
      <Element xsi:type="Line" Color="ZSEHO" StartLon="-124.4012478" StartLat="43.7238186" EndLon="-124.4078767" EndLat="43.7238186" Style="Solid" Thickness="0" />
      <Element xsi:type="Line" Color="ZSEHO" StartLon="-124.3977125" StartLat="43.7238186" EndLon="-124.4012478" EndLat="43.7238186" Style="Solid" Thickness="0" />
      <Element xsi:type="Line" Color="ZSEHO" StartLon="-124.5568011" StartLat="43.72647" EndLon="-124.5514983" EndLat="43.7339825" Style="Solid" Thickness="0" />
      <Element xsi:type="Line" Color="ZSEHO" StartLon="-124.4516258" StartLat="43.72647" EndLon="-124.4463231" EndLat="43.7339825" Style="Solid" Thickness="0" />
      <Element xsi:type="Line" Color="ZSEHO" StartLon="-124.3676625" StartLat="43.72647" EndLon="-124.3623594" EndLat="43.7339825" Style="Solid" Thickness="0" />
      <Element xsi:type="Line" Color="ZSEHO" StartLon="-124.4463231" StartLat="43.7339825" EndLon="-124.4463231" EndLat="43.7087936" Style="Solid" Thickness="0" />
      <Element xsi:type="Line" Color="ZSEHO" StartLon="-124.5373569" StartLat="43.7339825" EndLon="-124.5236578" EndLat="43.7339825" Style="Solid" Thickness="0" />
      <Element xsi:type="Line" Color="ZSEHO" StartLon="-124.5514983" StartLat="43.7339825" EndLon="-124.5514983" EndLat="43.7087936" Style="Solid" Thickness="0" />
      <Element xsi:type="Line" Color="ZSEHO" StartLon="-124.42025" StartLat="43.7339825" EndLon="-124.4308561" EndLat="43.7339825" Style="Solid" Thickness="0" />
      <Element xsi:type="Line" Color="ZSEHO" StartLon="-124.3486603" StartLat="43.7339825" EndLon="-124.3345189" EndLat="43.7339825" Style="Solid" Thickness="0" />
      <Element xsi:type="Line" Color="ZSEHO" StartLon="-124.3623594" StartLat="43.7339825" EndLon="-124.3623594" EndLat="43.7087936" Style="Solid" Thickness="0" />
      <Element xsi:type="Line" Color="ZSEHO" StartLon="-124.4114119" StartLat="43.7339825" EndLon="-124.3977125" EndLat="43.7339825" Style="Solid" Thickness="0" />
      <Element xsi:type="Line" Color="ZSEHO" StartLon="-124.1250522" StartLat="44.3199592" EndLon="-124.1215169" EndLat="44.3199592" Style="Solid" Thickness="0" />
      <Element xsi:type="Line" Color="ZSEHO" StartLon="-124.1091433" StartLat="44.3199592" EndLon="-124.1091433" EndLat="44.3248203" Style="Solid" Thickness="0" />
      <Element xsi:type="Line" Color="ZSEHO" StartLon="-124.0954442" StartLat="44.3199592" EndLon="-124.1091433" EndLat="44.3199592" Style="Solid" Thickness="0" />
      <Element xsi:type="Line" Color="ZSEHO" StartLon="-124.2350886" StartLat="44.3199592" EndLon="-124.2350886" EndLat="44.3248203" Style="Solid" Thickness="0" />
      <Element xsi:type="Line" Color="ZSEHO" StartLon="-124.2213892" StartLat="44.3199592" EndLon="-124.2350886" EndLat="44.3199592" Style="Solid" Thickness="0" />
      <Element xsi:type="Line" Color="ZSEHO" StartLon="-124.1215169" StartLat="44.3199592" EndLon="-124.1179817" EndLat="44.3226106" Style="Solid" Thickness="0" />
      <Element xsi:type="Line" Color="ZSEHO" StartLon="-124.0583233" StartLat="44.3199592" EndLon="-124.05523" EndLat="44.3226106" Style="Solid" Thickness="0" />
      <Element xsi:type="Line" Color="ZSEHO" StartLon="-124.0618586" StartLat="44.3199592" EndLon="-124.0583233" EndLat="44.3199592" Style="Solid" Thickness="0" />
      <Element xsi:type="Line" Color="ZSEHO" StartLon="-124.0410889" StartLat="44.3199592" EndLon="-124.0322506" EndLat="44.3451483" Style="Solid" Thickness="0" />
      <Element xsi:type="Line" Color="ZSEHO" StartLon="-124.0813028" StartLat="44.3199592" EndLon="-124.0813028" EndLat="44.3226106" Style="Solid" Thickness="0" />
      <Element xsi:type="Line" Color="ZSEHO" StartLon="-124.0830706" StartLat="44.3199592" EndLon="-124.0813028" EndLat="44.3199592" Style="Solid" Thickness="0" />
      <Element xsi:type="Line" Color="ZSEHO" StartLon="-124.0830706" StartLat="44.3199592" EndLon="-124.0830706" EndLat="44.3199592" Style="Solid" Thickness="0" />
      <Element xsi:type="Line" Color="ZSEHO" StartLon="-124.0830706" StartLat="44.3226106" EndLon="-124.0830706" EndLat="44.3199592" Style="Solid" Thickness="0" />
      <Element xsi:type="Line" Color="ZSEHO" StartLon="-124.1285875" StartLat="44.3226106" EndLon="-124.1250522" EndLat="44.3199592" Style="Solid" Thickness="0" />
      <Element xsi:type="Line" Color="ZSEHO" StartLon="-124.1179817" StartLat="44.3226106" EndLon="-124.1162139" EndLat="44.3248203" Style="Solid" Thickness="0" />
      <Element xsi:type="Line" Color="ZSEHO" StartLon="-124.0813028" StartLat="44.3226106" EndLon="-124.0830706" EndLat="44.3226106" Style="Solid" Thickness="0" />
      <Element xsi:type="Line" Color="ZSEHO" StartLon="-124.0653939" StartLat="44.3226106" EndLon="-124.0653939" EndLat="44.3226106" Style="Solid" Thickness="0" />
      <Element xsi:type="Line" Color="ZSEHO" StartLon="-124.0653939" StartLat="44.3226106" EndLon="-124.0618586" EndLat="44.3199592" Style="Solid" Thickness="0" />
      <Element xsi:type="Line" Color="ZSEHO" StartLon="-124.05523" StartLat="44.3226106" EndLon="-124.0534622" EndLat="44.3274717" Style="Solid" Thickness="0" />
      <Element xsi:type="Line" Color="ZSEHO" StartLon="-124.1162139" StartLat="44.3248203" EndLon="-124.1162139" EndLat="44.3301231" Style="Solid" Thickness="0" />
      <Element xsi:type="Line" Color="ZSEHO" StartLon="-124.2350886" StartLat="44.3248203" EndLon="-124.2213892" EndLat="44.3376356" Style="Solid" Thickness="0" />
      <Element xsi:type="Line" Color="ZSEHO" StartLon="-124.1091433" StartLat="44.3248203" EndLon="-124.0954442" EndLat="44.3376356" Style="Solid" Thickness="0" />
      <Element xsi:type="Line" Color="ZSEHO" StartLon="-124.1303553" StartLat="44.3248203" EndLon="-124.1285875" EndLat="44.3226106" Style="Solid" Thickness="0" />
      <Element xsi:type="Line" Color="ZSEHO" StartLon="-124.2421592" StartLat="44.3274717" EndLon="-124.2563003" EndLat="44.3274717" Style="Solid" Thickness="0" />
      <Element xsi:type="Line" Color="ZSEHO" StartLon="-124.2563003" StartLat="44.3274717" EndLon="-124.2474622" EndLat="44.3451483" Style="Solid" Thickness="0" />
      <Element xsi:type="Line" Color="ZSEHO" StartLon="-124.0534622" StartLat="44.3274717" EndLon="-124.0534622" EndLat="44.3376356" Style="Solid" Thickness="0" />
      <Element xsi:type="Line" Color="ZSEHO" StartLon="-124.0671617" StartLat="44.3274717" EndLon="-124.0653939" EndLat="44.3226106" Style="Solid" Thickness="0" />
      <Element xsi:type="Line" Color="ZSEHO" StartLon="-124.1811753" StartLat="44.3301231" EndLon="-124.1913392" EndLat="44.3301231" Style="Solid" Thickness="0" />
      <Element xsi:type="Line" Color="ZSEHO" StartLon="-124.1162139" StartLat="44.3301231" EndLon="-124.1179817" EndLat="44.3323328" Style="Solid" Thickness="0" />
      <Element xsi:type="Line" Color="ZSEHO" StartLon="-124.1179817" StartLat="44.3323328" EndLon="-124.1215169" EndLat="44.3349842" Style="Solid" Thickness="0" />
      <Element xsi:type="Line" Color="ZSEHO" StartLon="-124.1250522" StartLat="44.3349842" EndLon="-124.1179817" EndLat="44.3451483" Style="Solid" Thickness="0" />
      <Element xsi:type="Line" Color="ZSEHO" StartLon="-124.1215169" StartLat="44.3349842" EndLon="-124.1250522" EndLat="44.3349842" Style="Solid" Thickness="0" />
      <Element xsi:type="Line" Color="ZSEHO" StartLon="-124.1493575" StartLat="44.3376356" EndLon="-124.1440544" EndLat="44.3451483" Style="Solid" Thickness="0" />
      <Element xsi:type="Line" Color="ZSEHO" StartLon="-124.2213892" StartLat="44.3376356" EndLon="-124.2213892" EndLat="44.3424967" Style="Solid" Thickness="0" />
      <Element xsi:type="Line" Color="ZSEHO" StartLon="-124.0954442" StartLat="44.3376356" EndLon="-124.0954442" EndLat="44.3424967" Style="Solid" Thickness="0" />
      <Element xsi:type="Line" Color="ZSEHO" StartLon="-124.0534622" StartLat="44.3376356" EndLon="-124.05523" EndLat="44.3424967" Style="Solid" Thickness="0" />
      <Element xsi:type="Line" Color="ZSEHO" StartLon="-124.0671617" StartLat="44.3376356" EndLon="-124.0671617" EndLat="44.3274717" Style="Solid" Thickness="0" />
      <Element xsi:type="Line" Color="ZSEHO" StartLon="-124.0954442" StartLat="44.3424967" EndLon="-124.0989794" EndLat="44.3451483" Style="Solid" Thickness="0" />
      <Element xsi:type="Line" Color="ZSEHO" StartLon="-124.2213892" StartLat="44.3424967" EndLon="-124.2249244" EndLat="44.3451483" Style="Solid" Thickness="0" />
      <Element xsi:type="Line" Color="ZSEHO" StartLon="-124.05523" StartLat="44.3424967" EndLon="-124.0583233" EndLat="44.3451483" Style="Solid" Thickness="0" />
      <Element xsi:type="Line" Color="ZSEHO" StartLon="-124.0653939" StartLat="44.3424967" EndLon="-124.0671617" EndLat="44.3376356" Style="Solid" Thickness="0" />
      <Element xsi:type="Line" Color="ZSEHO" StartLon="-124.1440544" StartLat="44.3451483" EndLon="-124.1440544" EndLat="44.3199592" Style="Solid" Thickness="0" />
      <Element xsi:type="Line" Color="ZSEHO" StartLon="-124.1179817" StartLat="44.3451483" EndLon="-124.1285875" EndLat="44.3451483" Style="Solid" Thickness="0" />
      <Element xsi:type="Line" Color="ZSEHO" StartLon="-124.2249244" StartLat="44.3451483" EndLon="-124.2315533" EndLat="44.3451483" Style="Solid" Thickness="0" />
      <Element xsi:type="Line" Color="ZSEHO" StartLon="-124.2474622" StartLat="44.3451483" EndLon="-124.2474622" EndLat="44.3199592" Style="Solid" Thickness="0" />
      <Element xsi:type="Line" Color="ZSEHO" StartLon="-124.2315533" StartLat="44.3451483" EndLon="-124.2350886" EndLat="44.3424967" Style="Solid" Thickness="0" />
      <Element xsi:type="Line" Color="ZSEHO" StartLon="-124.0583233" StartLat="44.3451483" EndLon="-124.0618586" EndLat="44.3451483" Style="Solid" Thickness="0" />
      <Element xsi:type="Line" Color="ZSEHO" StartLon="-124.0322506" StartLat="44.3451483" EndLon="-124.0463917" EndLat="44.3451483" Style="Solid" Thickness="0" />
      <Element xsi:type="Line" Color="ZSEHO" StartLon="-124.0618586" StartLat="44.3451483" EndLon="-124.0653939" EndLat="44.3424967" Style="Solid" Thickness="0" />
      <Element xsi:type="Line" Color="ZSEHO" StartLon="-124.1056081" StartLat="44.3451483" EndLon="-124.1091433" EndLat="44.3424967" Style="Solid" Thickness="0" />
      <Element xsi:type="Line" Color="ZSEHO" StartLon="-124.0989794" StartLat="44.3451483" EndLon="-124.1056081" EndLat="44.3451483" Style="Solid" Thickness="0" />
      <Element xsi:type="Line" Color="ZSEHO" StartLon="-122.4758331" StartLat="44.4733031" EndLon="-122.4687622" EndLat="44.4733031" Style="Solid" Thickness="0" />
      <Element xsi:type="Line" Color="ZSEHO" StartLon="-122.3741931" StartLat="44.4733031" EndLon="-122.3741931" EndLat="44.4781639" Style="Solid" Thickness="0" />
      <Element xsi:type="Line" Color="ZSEHO" StartLon="-122.3604936" StartLat="44.4733031" EndLon="-122.3741931" EndLat="44.4733031" Style="Solid" Thickness="0" />
      <Element xsi:type="Line" Color="ZSEHO" StartLon="-122.4917419" StartLat="44.4733031" EndLon="-122.4882064" EndLat="44.4759544" Style="Solid" Thickness="0" />
      <Element xsi:type="Line" Color="ZSEHO" StartLon="-122.4948353" StartLat="44.4733031" EndLon="-122.4917419" EndLat="44.4733031" Style="Solid" Thickness="0" />
      <Element xsi:type="Line" Color="ZSEHO" StartLon="-122.4687622" StartLat="44.4733031" EndLon="-122.4652269" EndLat="44.4781639" Style="Solid" Thickness="0" />
      <Element xsi:type="Line" Color="ZSEHO" StartLon="-122.3428172" StartLat="44.4733031" EndLon="-122.3392819" EndLat="44.4759544" Style="Solid" Thickness="0" />
      <Element xsi:type="Line" Color="ZSEHO" StartLon="-122.3269083" StartLat="44.4733031" EndLon="-122.3269083" EndLat="44.4733031" Style="Solid" Thickness="0" />
      <Element xsi:type="Line" Color="ZSEHO" StartLon="-122.3008353" StartLat="44.4733031" EndLon="-122.2973" EndLat="44.4781639" Style="Solid" Thickness="0" />
      <Element xsi:type="Line" Color="ZSEHO" StartLon="-122.3079061" StartLat="44.4733031" EndLon="-122.3008353" EndLat="44.4733031" Style="Solid" Thickness="0" />
      <Element xsi:type="Line" Color="ZSEHO" StartLon="-122.3498878" StartLat="44.4733031" EndLon="-122.3428172" EndLat="44.4733031" Style="Solid" Thickness="0" />
      <Element xsi:type="Line" Color="ZSEHO" StartLon="-122.3251406" StartLat="44.4733031" EndLon="-122.3251406" EndLat="44.4759544" Style="Solid" Thickness="0" />
      <Element xsi:type="Line" Color="ZSEHO" StartLon="-122.3269083" StartLat="44.4733031" EndLon="-122.3251406" EndLat="44.4733031" Style="Solid" Thickness="0" />
      <Element xsi:type="Line" Color="ZSEHO" StartLon="-122.4983706" StartLat="44.4759544" EndLon="-122.4983706" EndLat="44.4759544" Style="Solid" Thickness="0" />
      <Element xsi:type="Line" Color="ZSEHO" StartLon="-122.4983706" StartLat="44.4759544" EndLon="-122.4948353" EndLat="44.4733031" Style="Solid" Thickness="0" />
      <Element xsi:type="Line" Color="ZSEHO" StartLon="-122.4882064" StartLat="44.4759544" EndLon="-122.4864389" EndLat="44.4808156" Style="Solid" Thickness="0" />
      <Element xsi:type="Line" Color="ZSEHO" StartLon="-122.3392819" StartLat="44.4759544" EndLon="-122.3392819" EndLat="44.4883281" Style="Solid" Thickness="0" />
      <Element xsi:type="Line" Color="ZSEHO" StartLon="-122.3251406" StartLat="44.4759544" EndLon="-122.3269083" EndLat="44.4759544" Style="Solid" Thickness="0" />
      <Element xsi:type="Line" Color="ZSEHO" StartLon="-122.3269083" StartLat="44.4759544" EndLon="-122.3269083" EndLat="44.4733031" Style="Solid" Thickness="0" />
      <Element xsi:type="Line" Color="ZSEHO" StartLon="-122.3534231" StartLat="44.4759544" EndLon="-122.3498878" EndLat="44.4733031" Style="Solid" Thickness="0" />
      <Element xsi:type="Line" Color="ZSEHO" StartLon="-122.4793683" StartLat="44.4781639" EndLon="-122.4758331" EndLat="44.4733031" Style="Solid" Thickness="0" />
      <Element xsi:type="Line" Color="ZSEHO" StartLon="-122.4652269" StartLat="44.4781639" EndLon="-122.4652269" EndLat="44.4834669" Style="Solid" Thickness="0" />
      <Element xsi:type="Line" Color="ZSEHO" StartLon="-122.3741931" StartLat="44.4781639" EndLon="-122.3604936" EndLat="44.4909794" Style="Solid" Thickness="0" />
      <Element xsi:type="Line" Color="ZSEHO" StartLon="-122.3114414" StartLat="44.4781639" EndLon="-122.3079061" EndLat="44.4733031" Style="Solid" Thickness="0" />
      <Element xsi:type="Line" Color="ZSEHO" StartLon="-122.2973" StartLat="44.4781639" EndLon="-122.2973" EndLat="44.4808156" Style="Solid" Thickness="0" />
      <Element xsi:type="Line" Color="ZSEHO" StartLon="-122.4864389" StartLat="44.4808156" EndLon="-122.4864389" EndLat="44.4909794" Style="Solid" Thickness="0" />
      <Element xsi:type="Line" Color="ZSEHO" StartLon="-122.5001381" StartLat="44.4808156" EndLon="-122.4983706" EndLat="44.4759544" Style="Solid" Thickness="0" />
      <Element xsi:type="Line" Color="ZSEHO" StartLon="-122.3114414" StartLat="44.4808156" EndLon="-122.3114414" EndLat="44.4781639" Style="Solid" Thickness="0" />
      <Element xsi:type="Line" Color="ZSEHO" StartLon="-122.2973" StartLat="44.4808156" EndLon="-122.3026031" EndLat="44.4856767" Style="Solid" Thickness="0" />
      <Element xsi:type="Line" Color="ZSEHO" StartLon="-122.4652269" StartLat="44.4834669" EndLon="-122.4687622" EndLat="44.4883281" Style="Solid" Thickness="0" />
      <Element xsi:type="Line" Color="ZSEHO" StartLon="-122.4250131" StartLat="44.4834669" EndLon="-122.4356189" EndLat="44.4834669" Style="Solid" Thickness="0" />
      <Element xsi:type="Line" Color="ZSEHO" StartLon="-122.3026031" StartLat="44.4856767" EndLon="-122.3061383" EndLat="44.4856767" Style="Solid" Thickness="0" />
      <Element xsi:type="Line" Color="ZSEHO" StartLon="-122.3534231" StartLat="44.4856767" EndLon="-122.3534231" EndLat="44.4984919" Style="Solid" Thickness="0" />
      <Element xsi:type="Line" Color="ZSEHO" StartLon="-122.3026031" StartLat="44.4856767" EndLon="-122.2973" EndLat="44.4909794" Style="Solid" Thickness="0" />
      <Element xsi:type="Line" Color="ZSEHO" StartLon="-122.3061383" StartLat="44.4856767" EndLon="-122.3114414" EndLat="44.4808156" Style="Solid" Thickness="0" />
      <Element xsi:type="Line" Color="ZSEHO" StartLon="-122.4687622" StartLat="44.4883281" EndLon="-122.4758331" EndLat="44.4883281" Style="Solid" Thickness="0" />
      <Element xsi:type="Line" Color="ZSEHO" StartLon="-122.4758331" StartLat="44.4883281" EndLon="-122.4793683" EndLat="44.4834669" Style="Solid" Thickness="0" />
      <Element xsi:type="Line" Color="ZSEHO" StartLon="-122.3498878" StartLat="44.4883281" EndLon="-122.3534231" EndLat="44.4856767" Style="Solid" Thickness="0" />
      <Element xsi:type="Line" Color="ZSEHO" StartLon="-122.3392819" StartLat="44.4883281" EndLon="-122.3428172" EndLat="44.4883281" Style="Solid" Thickness="0" />
      <Element xsi:type="Line" Color="ZSEHO" StartLon="-122.3428172" StartLat="44.4883281" EndLon="-122.3498878" EndLat="44.4883281" Style="Solid" Thickness="0" />
      <Element xsi:type="Line" Color="ZSEHO" StartLon="-122.3936372" StartLat="44.4909794" EndLon="-122.3883342" EndLat="44.4984919" Style="Solid" Thickness="0" />
      <Element xsi:type="Line" Color="ZSEHO" StartLon="-122.4864389" StartLat="44.4909794" EndLon="-122.4882064" EndLat="44.4958406" Style="Solid" Thickness="0" />
      <Element xsi:type="Line" Color="ZSEHO" StartLon="-122.5001381" StartLat="44.4909794" EndLon="-122.5001381" EndLat="44.4808156" Style="Solid" Thickness="0" />
      <Element xsi:type="Line" Color="ZSEHO" StartLon="-122.2973" StartLat="44.4909794" EndLon="-122.2973" EndLat="44.4931892" Style="Solid" Thickness="0" />
      <Element xsi:type="Line" Color="ZSEHO" StartLon="-122.3114414" StartLat="44.4909794" EndLon="-122.3061383" EndLat="44.4856767" Style="Solid" Thickness="0" />
      <Element xsi:type="Line" Color="ZSEHO" StartLon="-122.3604936" StartLat="44.4909794" EndLon="-122.3604936" EndLat="44.4958406" Style="Solid" Thickness="0" />
      <Element xsi:type="Line" Color="ZSEHO" StartLon="-122.4793683" StartLat="44.4931892" EndLon="-122.4793683" EndLat="44.4781639" Style="Solid" Thickness="0" />
      <Element xsi:type="Line" Color="ZSEHO" StartLon="-122.3114414" StartLat="44.4931892" EndLon="-122.3114414" EndLat="44.4909794" Style="Solid" Thickness="0" />
      <Element xsi:type="Line" Color="ZSEHO" StartLon="-122.2973" StartLat="44.4931892" EndLon="-122.3008353" EndLat="44.4984919" Style="Solid" Thickness="0" />
      <Element xsi:type="Line" Color="ZSEHO" StartLon="-122.4882064" StartLat="44.4958406" EndLon="-122.4917419" EndLat="44.4984919" Style="Solid" Thickness="0" />
      <Element xsi:type="Line" Color="ZSEHO" StartLon="-122.4983706" StartLat="44.4958406" EndLon="-122.5001381" EndLat="44.4909794" Style="Solid" Thickness="0" />
      <Element xsi:type="Line" Color="ZSEHO" StartLon="-122.3604936" StartLat="44.4958406" EndLon="-122.3640289" EndLat="44.4984919" Style="Solid" Thickness="0" />
      <Element xsi:type="Line" Color="ZSEHO" StartLon="-122.4652269" StartLat="44.4958406" EndLon="-122.4687622" EndLat="44.4984919" Style="Solid" Thickness="0" />
      <Element xsi:type="Line" Color="ZSEHO" StartLon="-122.4687622" StartLat="44.4984919" EndLon="-122.4758331" EndLat="44.4984919" Style="Solid" Thickness="0" />
      <Element xsi:type="Line" Color="ZSEHO" StartLon="-122.3883342" StartLat="44.4984919" EndLon="-122.3883342" EndLat="44.4733031" Style="Solid" Thickness="0" />
      <Element xsi:type="Line" Color="ZSEHO" StartLon="-122.4758331" StartLat="44.4984919" EndLon="-122.4793683" EndLat="44.4931892" Style="Solid" Thickness="0" />
      <Element xsi:type="Line" Color="ZSEHO" StartLon="-122.4948353" StartLat="44.4984919" EndLon="-122.4983706" EndLat="44.4958406" Style="Solid" Thickness="0" />
      <Element xsi:type="Line" Color="ZSEHO" StartLon="-122.4917419" StartLat="44.4984919" EndLon="-122.4948353" EndLat="44.4984919" Style="Solid" Thickness="0" />
      <Element xsi:type="Line" Color="ZSEHO" StartLon="-122.3079061" StartLat="44.4984919" EndLon="-122.3114414" EndLat="44.4931892" Style="Solid" Thickness="0" />
      <Element xsi:type="Line" Color="ZSEHO" StartLon="-122.3008353" StartLat="44.4984919" EndLon="-122.3079061" EndLat="44.4984919" Style="Solid" Thickness="0" />
      <Element xsi:type="Line" Color="ZSEHO" StartLon="-122.3534231" StartLat="44.4984919" EndLon="-122.3392819" EndLat="44.4984919" Style="Solid" Thickness="0" />
      <Element xsi:type="Line" Color="ZSEHO" StartLon="-122.3706578" StartLat="44.4984919" EndLon="-122.3741931" EndLat="44.4958406" Style="Solid" Thickness="0" />
      <Element xsi:type="Line" Color="ZSEHO" StartLon="-122.3640289" StartLat="44.4984919" EndLon="-122.3706578" EndLat="44.4984919" Style="Solid" Thickness="0" />
      <Element xsi:type="Line" Color="ZSEHO" StartLon="-122.85" StartLat="44.5605122" EndLon="-122.7833333" EndLat="45.0833333" Style="Solid" Thickness="0" />
      <Element xsi:type="Line" Color="ZSEHO" StartLon="-122.85" StartLat="44.5605122" EndLon="-123.9316233" EndLat="43.7115794" Style="Solid" Thickness="0" />
      <Element xsi:type="Line" Color="ZSEHO" StartLon="-123.3066294" StartLat="44.9492433" EndLon="-123.3030942" EndLat="44.9492433" Style="Solid" Thickness="0" />
      <Element xsi:type="Line" Color="ZSEHO" StartLon="-123.2911625" StartLat="44.9492433" EndLon="-123.2911625" EndLat="44.9541044" Style="Solid" Thickness="0" />
      <Element xsi:type="Line" Color="ZSEHO" StartLon="-123.2770211" StartLat="44.9492433" EndLon="-123.2911625" EndLat="44.9492433" Style="Solid" Thickness="0" />
      <Element xsi:type="Line" Color="ZSEHO" StartLon="-123.4171075" StartLat="44.9492433" EndLon="-123.4171075" EndLat="44.9541044" Style="Solid" Thickness="0" />
      <Element xsi:type="Line" Color="ZSEHO" StartLon="-123.4029664" StartLat="44.9492433" EndLon="-123.4171075" EndLat="44.9492433" Style="Solid" Thickness="0" />
      <Element xsi:type="Line" Color="ZSEHO" StartLon="-123.3030942" StartLat="44.9492433" EndLon="-123.3000006" EndLat="44.9514528" Style="Solid" Thickness="0" />
      <Element xsi:type="Line" Color="ZSEHO" StartLon="-123.2403425" StartLat="44.9492433" EndLon="-123.2368072" EndLat="44.9514528" Style="Solid" Thickness="0" />
      <Element xsi:type="Line" Color="ZSEHO" StartLon="-123.2438778" StartLat="44.9492433" EndLon="-123.2403425" EndLat="44.9492433" Style="Solid" Thickness="0" />
      <Element xsi:type="Line" Color="ZSEHO" StartLon="-123.2226658" StartLat="44.9492433" EndLon="-123.2142694" EndLat="44.9739903" Style="Solid" Thickness="0" />
      <Element xsi:type="Line" Color="ZSEHO" StartLon="-123.26288" StartLat="44.9492433" EndLon="-123.26288" EndLat="44.9514528" Style="Solid" Thickness="0" />
      <Element xsi:type="Line" Color="ZSEHO" StartLon="-123.2646478" StartLat="44.9492433" EndLon="-123.26288" EndLat="44.9492433" Style="Solid" Thickness="0" />
      <Element xsi:type="Line" Color="ZSEHO" StartLon="-123.2646478" StartLat="44.9492433" EndLon="-123.2646478" EndLat="44.9492433" Style="Solid" Thickness="0" />
      <Element xsi:type="Line" Color="ZSEHO" StartLon="-123.2646478" StartLat="44.9514528" EndLon="-123.2646478" EndLat="44.9492433" Style="Solid" Thickness="0" />
      <Element xsi:type="Line" Color="ZSEHO" StartLon="-123.3101647" StartLat="44.9514528" EndLon="-123.3066294" EndLat="44.9492433" Style="Solid" Thickness="0" />
      <Element xsi:type="Line" Color="ZSEHO" StartLon="-123.3000006" StartLat="44.9514528" EndLon="-123.2982331" EndLat="44.9541044" Style="Solid" Thickness="0" />
      <Element xsi:type="Line" Color="ZSEHO" StartLon="-123.26288" StartLat="44.9514528" EndLon="-123.2646478" EndLat="44.9514528" Style="Solid" Thickness="0" />
      <Element xsi:type="Line" Color="ZSEHO" StartLon="-123.2474131" StartLat="44.9514528" EndLon="-123.2474131" EndLat="44.9514528" Style="Solid" Thickness="0" />
      <Element xsi:type="Line" Color="ZSEHO" StartLon="-123.2474131" StartLat="44.9514528" EndLon="-123.2438778" EndLat="44.9492433" Style="Solid" Thickness="0" />
      <Element xsi:type="Line" Color="ZSEHO" StartLon="-123.2368072" StartLat="44.9514528" EndLon="-123.2350394" EndLat="44.9567558" Style="Solid" Thickness="0" />
      <Element xsi:type="Line" Color="ZSEHO" StartLon="-123.2982331" StartLat="44.9541044" EndLon="-123.2982331" EndLat="44.9589653" Style="Solid" Thickness="0" />
      <Element xsi:type="Line" Color="ZSEHO" StartLon="-123.4171075" StartLat="44.9541044" EndLon="-123.4029664" EndLat="44.9664778" Style="Solid" Thickness="0" />
      <Element xsi:type="Line" Color="ZSEHO" StartLon="-123.2911625" StartLat="44.9541044" EndLon="-123.2770211" EndLat="44.9664778" Style="Solid" Thickness="0" />
      <Element xsi:type="Line" Color="ZSEHO" StartLon="-123.3119322" StartLat="44.9541044" EndLon="-123.3101647" EndLat="44.9514528" Style="Solid" Thickness="0" />
      <Element xsi:type="Line" Color="ZSEHO" StartLon="-123.4241783" StartLat="44.9567558" EndLon="-123.4378775" EndLat="44.9567558" Style="Solid" Thickness="0" />
      <Element xsi:type="Line" Color="ZSEHO" StartLon="-123.4378775" StartLat="44.9567558" EndLon="-123.4290392" EndLat="44.9739903" Style="Solid" Thickness="0" />
      <Element xsi:type="Line" Color="ZSEHO" StartLon="-123.2350394" StartLat="44.9567558" EndLon="-123.2350394" EndLat="44.9664778" Style="Solid" Thickness="0" />
      <Element xsi:type="Line" Color="ZSEHO" StartLon="-123.2491806" StartLat="44.9567558" EndLon="-123.2474131" EndLat="44.9514528" Style="Solid" Thickness="0" />
      <Element xsi:type="Line" Color="ZSEHO" StartLon="-123.3627522" StartLat="44.9589653" EndLon="-123.3733583" EndLat="44.9589653" Style="Solid" Thickness="0" />
      <Element xsi:type="Line" Color="ZSEHO" StartLon="-123.2982331" StartLat="44.9589653" EndLon="-123.3000006" EndLat="44.9616169" Style="Solid" Thickness="0" />
      <Element xsi:type="Line" Color="ZSEHO" StartLon="-123.3000006" StartLat="44.9616169" EndLon="-123.3030942" EndLat="44.9642683" Style="Solid" Thickness="0" />
      <Element xsi:type="Line" Color="ZSEHO" StartLon="-123.3066294" StartLat="44.9642683" EndLon="-123.3000006" EndLat="44.9739903" Style="Solid" Thickness="0" />
      <Element xsi:type="Line" Color="ZSEHO" StartLon="-123.3030942" StartLat="44.9642683" EndLon="-123.3066294" EndLat="44.9642683" Style="Solid" Thickness="0" />
      <Element xsi:type="Line" Color="ZSEHO" StartLon="-123.3313764" StartLat="44.9664778" EndLon="-123.3260736" EndLat="44.9739903" Style="Solid" Thickness="0" />
      <Element xsi:type="Line" Color="ZSEHO" StartLon="-123.4029664" StartLat="44.9664778" EndLon="-123.4029664" EndLat="44.9717808" Style="Solid" Thickness="0" />
      <Element xsi:type="Line" Color="ZSEHO" StartLon="-123.2770211" StartLat="44.9664778" EndLon="-123.2770211" EndLat="44.9717808" Style="Solid" Thickness="0" />
      <Element xsi:type="Line" Color="ZSEHO" StartLon="-123.2350394" StartLat="44.9664778" EndLon="-123.2368072" EndLat="44.9717808" Style="Solid" Thickness="0" />
      <Element xsi:type="Line" Color="ZSEHO" StartLon="-123.2491806" StartLat="44.9664778" EndLon="-123.2491806" EndLat="44.9567558" Style="Solid" Thickness="0" />
      <Element xsi:type="Line" Color="ZSEHO" StartLon="-123.2770211" StartLat="44.9717808" EndLon="-123.2805564" EndLat="44.9739903" Style="Solid" Thickness="0" />
      <Element xsi:type="Line" Color="ZSEHO" StartLon="-123.4029664" StartLat="44.9717808" EndLon="-123.4065017" EndLat="44.9739903" Style="Solid" Thickness="0" />
      <Element xsi:type="Line" Color="ZSEHO" StartLon="-123.2368072" StartLat="44.9717808" EndLon="-123.2403425" EndLat="44.9739903" Style="Solid" Thickness="0" />
      <Element xsi:type="Line" Color="ZSEHO" StartLon="-123.2474131" StartLat="44.9717808" EndLon="-123.2491806" EndLat="44.9664778" Style="Solid" Thickness="0" />
      <Element xsi:type="Line" Color="ZSEHO" StartLon="-123.3260736" StartLat="44.9739903" EndLon="-123.3260736" EndLat="44.9492433" Style="Solid" Thickness="0" />
      <Element xsi:type="Line" Color="ZSEHO" StartLon="-123.3000006" StartLat="44.9739903" EndLon="-123.3101647" EndLat="44.9739903" Style="Solid" Thickness="0" />
      <Element xsi:type="Line" Color="ZSEHO" StartLon="-123.4065017" StartLat="44.9739903" EndLon="-123.4135722" EndLat="44.9739903" Style="Solid" Thickness="0" />
      <Element xsi:type="Line" Color="ZSEHO" StartLon="-123.4290392" StartLat="44.9739903" EndLon="-123.4290392" EndLat="44.9492433" Style="Solid" Thickness="0" />
      <Element xsi:type="Line" Color="ZSEHO" StartLon="-123.4135722" StartLat="44.9739903" EndLon="-123.4171075" EndLat="44.9717808" Style="Solid" Thickness="0" />
      <Element xsi:type="Line" Color="ZSEHO" StartLon="-123.2403425" StartLat="44.9739903" EndLon="-123.2438778" EndLat="44.9739903" Style="Solid" Thickness="0" />
      <Element xsi:type="Line" Color="ZSEHO" StartLon="-123.2142694" StartLat="44.9739903" EndLon="-123.2279689" EndLat="44.9739903" Style="Solid" Thickness="0" />
      <Element xsi:type="Line" Color="ZSEHO" StartLon="-123.2438778" StartLat="44.9739903" EndLon="-123.2474131" EndLat="44.9717808" Style="Solid" Thickness="0" />
      <Element xsi:type="Line" Color="ZSEHO" StartLon="-123.2876272" StartLat="44.9739903" EndLon="-123.2911625" EndLat="44.9717808" Style="Solid" Thickness="0" />
      <Element xsi:type="Line" Color="ZSEHO" StartLon="-123.2805564" StartLat="44.9739903" EndLon="-123.2876272" EndLat="44.9739903" Style="Solid" Thickness="0" />
      <Element xsi:type="Line" Color="ZSEHO" StartLon="-122.85" StartLat="45.3333333" EndLon="-122.7833333" EndLat="45.0833333" Style="Solid" Thickness="0" />
      <Element xsi:type="Line" Color="TRACON" StartLon="0" StartLat="0" EndLon="0" EndLat="0" Style="Solid" Thickness="0" />
      <Element xsi:type="Line" Color="ZSEHO" StartLon="-122.4166667" StartLat="41.3333333" EndLon="-122.55" EndLat="43.4666667" Style="Solid" Thickness="0" />
      <Element xsi:type="Line" Color="ZSEHO" StartLon="-123.3521464" StartLat="41.9168364" EndLon="-123.3486111" EndLat="41.9168364" Style="Solid" Thickness="0" />
      <Element xsi:type="Line" Color="ZSEHO" StartLon="-123.3260736" StartLat="41.9168364" EndLon="-123.3225383" EndLat="41.9190458" Style="Solid" Thickness="0" />
      <Element xsi:type="Line" Color="ZSEHO" StartLon="-123.3486111" StartLat="41.9168364" EndLon="-123.3450758" EndLat="41.9190458" Style="Solid" Thickness="0" />
      <Element xsi:type="Line" Color="ZSEHO" StartLon="-123.4520186" StartLat="41.9168364" EndLon="-123.4484833" EndLat="41.9190458" Style="Solid" Thickness="0" />
      <Element xsi:type="Line" Color="ZSEHO" StartLon="-123.4590894" StartLat="41.9168364" EndLon="-123.4520186" EndLat="41.9168364" Style="Solid" Thickness="0" />
      <Element xsi:type="Line" Color="ZSEHO" StartLon="-123.3327022" StartLat="41.9168364" EndLon="-123.3260736" EndLat="41.9168364" Style="Solid" Thickness="0" />
      <Element xsi:type="Line" Color="ZSEHO" StartLon="-123.26288" StartLat="41.9168364" EndLon="-123.2593447" EndLat="41.9190458" Style="Solid" Thickness="0" />
      <Element xsi:type="Line" Color="ZSEHO" StartLon="-123.2699506" StartLat="41.9168364" EndLon="-123.26288" EndLat="41.9168364" Style="Solid" Thickness="0" />
      <Element xsi:type="Line" Color="ZSEHO" StartLon="-123.3101647" StartLat="41.9168364" EndLon="-123.3101647" EndLat="41.9168364" Style="Solid" Thickness="0" />
      <Element xsi:type="Line" Color="ZSEHO" StartLon="-123.3083969" StartLat="41.9168364" EndLon="-123.3083969" EndLat="41.9190458" Style="Solid" Thickness="0" />
      <Element xsi:type="Line" Color="ZSEHO" StartLon="-123.3101647" StartLat="41.9168364" EndLon="-123.3083969" EndLat="41.9168364" Style="Solid" Thickness="0" />
      <Element xsi:type="Line" Color="ZSEHO" StartLon="-123.3556817" StartLat="41.9190458" EndLon="-123.3521464" EndLat="41.9168364" Style="Solid" Thickness="0" />
      <Element xsi:type="Line" Color="ZSEHO" StartLon="-123.3225383" StartLat="41.9190458" EndLon="-123.3225383" EndLat="41.9318614" Style="Solid" Thickness="0" />
      <Element xsi:type="Line" Color="ZSEHO" StartLon="-123.3450758" StartLat="41.9190458" EndLon="-123.3433081" EndLat="41.9216975" Style="Solid" Thickness="0" />
      <Element xsi:type="Line" Color="ZSEHO" StartLon="-123.4484833" StartLat="41.9190458" EndLon="-123.4484833" EndLat="41.9318614" Style="Solid" Thickness="0" />
      <Element xsi:type="Line" Color="ZSEHO" StartLon="-123.4621828" StartLat="41.9190458" EndLon="-123.4590894" EndLat="41.9168364" Style="Solid" Thickness="0" />
      <Element xsi:type="Line" Color="ZSEHO" StartLon="-123.2593447" StartLat="41.9190458" EndLon="-123.2593447" EndLat="41.9318614" Style="Solid" Thickness="0" />
      <Element xsi:type="Line" Color="ZSEHO" StartLon="-123.2734858" StartLat="41.9190458" EndLon="-123.2699506" EndLat="41.9168364" Style="Solid" Thickness="0" />
      <Element xsi:type="Line" Color="ZSEHO" StartLon="-123.3083969" StartLat="41.9190458" EndLon="-123.3101647" EndLat="41.9190458" Style="Solid" Thickness="0" />
      <Element xsi:type="Line" Color="ZSEHO" StartLon="-123.3362375" StartLat="41.9190458" EndLon="-123.3327022" EndLat="41.9168364" Style="Solid" Thickness="0" />
      <Element xsi:type="Line" Color="ZSEHO" StartLon="-123.3101647" StartLat="41.9190458" EndLon="-123.3101647" EndLat="41.9168364" Style="Solid" Thickness="0" />
      <Element xsi:type="Line" Color="ZSEHO" StartLon="-123.3433081" StartLat="41.9216975" EndLon="-123.3433081" EndLat="41.9265583" Style="Solid" Thickness="0" />
      <Element xsi:type="Line" Color="ZSEHO" StartLon="-123.3574494" StartLat="41.9216975" EndLon="-123.3556817" EndLat="41.9190458" Style="Solid" Thickness="0" />
      <Element xsi:type="Line" Color="ZSEHO" StartLon="-123.4082694" StartLat="41.9265583" EndLon="-123.4184333" EndLat="41.9265583" Style="Solid" Thickness="0" />
      <Element xsi:type="Line" Color="ZSEHO" StartLon="-123.3433081" StartLat="41.9265583" EndLon="-123.3450758" EndLat="41.92921" Style="Solid" Thickness="0" />
      <Element xsi:type="Line" Color="ZSEHO" StartLon="-123.3450758" StartLat="41.92921" EndLon="-123.3486111" EndLat="41.9318614" Style="Solid" Thickness="0" />
      <Element xsi:type="Line" Color="ZSEHO" StartLon="-123.4621828" StartLat="41.92921" EndLon="-123.4621828" EndLat="41.9415833" Style="Solid" Thickness="0" />
      <Element xsi:type="Line" Color="ZSEHO" StartLon="-123.2734858" StartLat="41.92921" EndLon="-123.2734858" EndLat="41.9415833" Style="Solid" Thickness="0" />
      <Element xsi:type="Line" Color="ZSEHO" StartLon="-123.3362375" StartLat="41.92921" EndLon="-123.3362375" EndLat="41.9415833" Style="Solid" Thickness="0" />
      <Element xsi:type="Line" Color="ZSEHO" StartLon="-123.3521464" StartLat="41.9318614" EndLon="-123.3450758" EndLat="41.9415833" Style="Solid" Thickness="0" />
      <Element xsi:type="Line" Color="ZSEHO" StartLon="-123.3486111" StartLat="41.9318614" EndLon="-123.3521464" EndLat="41.9318614" Style="Solid" Thickness="0" />
      <Element xsi:type="Line" Color="ZSEHO" StartLon="-123.4484833" StartLat="41.9318614" EndLon="-123.4520186" EndLat="41.9318614" Style="Solid" Thickness="0" />
      <Element xsi:type="Line" Color="ZSEHO" StartLon="-123.4590894" StartLat="41.9318614" EndLon="-123.4621828" EndLat="41.92921" Style="Solid" Thickness="0" />
      <Element xsi:type="Line" Color="ZSEHO" StartLon="-123.4520186" StartLat="41.9318614" EndLon="-123.4590894" EndLat="41.9318614" Style="Solid" Thickness="0" />
      <Element xsi:type="Line" Color="ZSEHO" StartLon="-123.3327022" StartLat="41.9318614" EndLon="-123.3362375" EndLat="41.92921" Style="Solid" Thickness="0" />
      <Element xsi:type="Line" Color="ZSEHO" StartLon="-123.26288" StartLat="41.9318614" EndLon="-123.2699506" EndLat="41.9318614" Style="Solid" Thickness="0" />
      <Element xsi:type="Line" Color="ZSEHO" StartLon="-123.2593447" StartLat="41.9318614" EndLon="-123.26288" EndLat="41.9318614" Style="Solid" Thickness="0" />
      <Element xsi:type="Line" Color="ZSEHO" StartLon="-123.2699506" StartLat="41.9318614" EndLon="-123.2734858" EndLat="41.92921" Style="Solid" Thickness="0" />
      <Element xsi:type="Line" Color="ZSEHO" StartLon="-123.3260736" StartLat="41.9318614" EndLon="-123.3327022" EndLat="41.9318614" Style="Solid" Thickness="0" />
      <Element xsi:type="Line" Color="ZSEHO" StartLon="-123.3225383" StartLat="41.9318614" EndLon="-123.3260736" EndLat="41.9318614" Style="Solid" Thickness="0" />
      <Element xsi:type="Line" Color="ZSEHO" StartLon="-123.4816269" StartLat="41.9340708" EndLon="-123.4763239" EndLat="41.9415833" Style="Solid" Thickness="0" />
      <Element xsi:type="Line" Color="ZSEHO" StartLon="-123.3764517" StartLat="41.9340708" EndLon="-123.3715906" EndLat="41.9415833" Style="Solid" Thickness="0" />
      <Element xsi:type="Line" Color="ZSEHO" StartLon="-123.2924881" StartLat="41.9340708" EndLon="-123.2876272" EndLat="41.9415833" Style="Solid" Thickness="0" />
      <Element xsi:type="Line" Color="ZSEHO" StartLon="-123.3715906" StartLat="41.9415833" EndLon="-123.3715906" EndLat="41.9168364" Style="Solid" Thickness="0" />
      <Element xsi:type="Line" Color="ZSEHO" StartLon="-123.4621828" StartLat="41.9415833" EndLon="-123.4484833" EndLat="41.9415833" Style="Solid" Thickness="0" />
      <Element xsi:type="Line" Color="ZSEHO" StartLon="-123.4763239" StartLat="41.9415833" EndLon="-123.4763239" EndLat="41.9168364" Style="Solid" Thickness="0" />
      <Element xsi:type="Line" Color="ZSEHO" StartLon="-123.3450758" StartLat="41.9415833" EndLon="-123.3556817" EndLat="41.9415833" Style="Solid" Thickness="0" />
      <Element xsi:type="Line" Color="ZSEHO" StartLon="-123.2734858" StartLat="41.9415833" EndLon="-123.2593447" EndLat="41.9415833" Style="Solid" Thickness="0" />
      <Element xsi:type="Line" Color="ZSEHO" StartLon="-123.2876272" StartLat="41.9415833" EndLon="-123.2876272" EndLat="41.9168364" Style="Solid" Thickness="0" />
      <Element xsi:type="Line" Color="ZSEHO" StartLon="-123.3362375" StartLat="41.9415833" EndLon="-123.3225383" EndLat="41.9415833" Style="Solid" Thickness="0" />
      <Element xsi:type="Line" Color="ZSEHO" StartLon="-122.1670569" StartLat="42.3600442" EndLon="-122.1670569" EndLat="42.3626956" Style="Solid" Thickness="0" />
      <Element xsi:type="Line" Color="ZSEHO" StartLon="-122.2108064" StartLat="42.3600442" EndLon="-122.2072711" EndLat="42.3600442" Style="Solid" Thickness="0" />
      <Element xsi:type="Line" Color="ZSEHO" StartLon="-122.2072711" StartLat="42.3600442" EndLon="-122.2037358" EndLat="42.3626956" Style="Solid" Thickness="0" />
      <Element xsi:type="Line" Color="ZSEHO" StartLon="-122.1688247" StartLat="42.3600442" EndLon="-122.1670569" EndLat="42.3600442" Style="Solid" Thickness="0" />
      <Element xsi:type="Line" Color="ZSEHO" StartLon="-122.1427519" StartLat="42.3600442" EndLon="-122.1493806" EndLat="42.3600442" Style="Solid" Thickness="0" />
      <Element xsi:type="Line" Color="ZSEHO" StartLon="-122.1493806" StartLat="42.3600442" EndLon="-122.1529158" EndLat="42.3626956" Style="Solid" Thickness="0" />
      <Element xsi:type="Line" Color="ZSEHO" StartLon="-122.1688247" StartLat="42.3600442" EndLon="-122.1688247" EndLat="42.3600442" Style="Solid" Thickness="0" />
      <Element xsi:type="Line" Color="ZSEHO" StartLon="-122.2143417" StartLat="42.3626956" EndLon="-122.2108064" EndLat="42.3600442" Style="Solid" Thickness="0" />
      <Element xsi:type="Line" Color="ZSEHO" StartLon="-122.2037358" StartLat="42.3626956" EndLon="-122.2019681" EndLat="42.3653469" Style="Solid" Thickness="0" />
      <Element xsi:type="Line" Color="ZSEHO" StartLon="-122.1670569" StartLat="42.3626956" EndLon="-122.1688247" EndLat="42.3626956" Style="Solid" Thickness="0" />
      <Element xsi:type="Line" Color="ZSEHO" StartLon="-122.1688247" StartLat="42.3626956" EndLon="-122.1688247" EndLat="42.3600442" Style="Solid" Thickness="0" />
      <Element xsi:type="Line" Color="ZSEHO" StartLon="-122.2019681" StartLat="42.3653469" EndLon="-122.2019681" EndLat="42.3702081" Style="Solid" Thickness="0" />
      <Element xsi:type="Line" Color="ZSEHO" StartLon="-122.2161094" StartLat="42.3653469" EndLon="-122.2143417" EndLat="42.3626956" Style="Solid" Thickness="0" />
      <Element xsi:type="Line" Color="ZSEHO" StartLon="-122.1392167" StartLat="42.3653469" EndLon="-122.1427519" EndLat="42.3600442" Style="Solid" Thickness="0" />
      <Element xsi:type="Line" Color="ZSEHO" StartLon="-122.3071433" StartLat="42.3675567" EndLon="-122.3208428" EndLat="42.3675567" Style="Solid" Thickness="0" />
      <Element xsi:type="Line" Color="ZSEHO" StartLon="-122.3208428" StartLat="42.3675567" EndLon="-122.3124464" EndLat="42.3852331" Style="Solid" Thickness="0" />
      <Element xsi:type="Line" Color="ZSEHO" StartLon="-122.1811983" StartLat="42.3675567" EndLon="-122.1948975" EndLat="42.3675567" Style="Solid" Thickness="0" />
      <Element xsi:type="Line" Color="ZSEHO" StartLon="-122.1948975" StartLat="42.3675567" EndLon="-122.1865011" EndLat="42.3852331" Style="Solid" Thickness="0" />
      <Element xsi:type="Line" Color="ZSEHO" StartLon="-122.2019681" StartLat="42.3702081" EndLon="-122.2037358" EndLat="42.3728594" Style="Solid" Thickness="0" />
      <Element xsi:type="Line" Color="ZSEHO" StartLon="-122.2669294" StartLat="42.3702081" EndLon="-122.2770933" EndLat="42.3702081" Style="Solid" Thickness="0" />
      <Element xsi:type="Line" Color="ZSEHO" StartLon="-122.1427519" StartLat="42.3702081" EndLon="-122.1493806" EndLat="42.3702081" Style="Solid" Thickness="0" />
      <Element xsi:type="Line" Color="ZSEHO" StartLon="-122.1493806" StartLat="42.3702081" EndLon="-122.1529158" EndLat="42.3750692" Style="Solid" Thickness="0" />
      <Element xsi:type="Line" Color="ZSEHO" StartLon="-122.2037358" StartLat="42.3728594" EndLon="-122.2072711" EndLat="42.3750692" Style="Solid" Thickness="0" />
      <Element xsi:type="Line" Color="ZSEHO" StartLon="-122.2072711" StartLat="42.3750692" EndLon="-122.2108064" EndLat="42.3750692" Style="Solid" Thickness="0" />
      <Element xsi:type="Line" Color="ZSEHO" StartLon="-122.2108064" StartLat="42.3750692" EndLon="-122.2037358" EndLat="42.3852331" Style="Solid" Thickness="0" />
      <Element xsi:type="Line" Color="ZSEHO" StartLon="-122.1392167" StartLat="42.3750692" EndLon="-122.1427519" EndLat="42.3702081" Style="Solid" Thickness="0" />
      <Element xsi:type="Line" Color="ZSEHO" StartLon="-122.1529158" StartLat="42.3750692" EndLon="-122.1529158" EndLat="42.3803722" Style="Solid" Thickness="0" />
      <Element xsi:type="Line" Color="ZSEHO" StartLon="-122.3402869" StartLat="42.3777206" EndLon="-122.3349839" EndLat="42.3852331" Style="Solid" Thickness="0" />
      <Element xsi:type="Line" Color="ZSEHO" StartLon="-122.2351117" StartLat="42.3777206" EndLon="-122.2302506" EndLat="42.3852331" Style="Solid" Thickness="0" />
      <Element xsi:type="Line" Color="ZSEHO" StartLon="-122.1392167" StartLat="42.3803722" EndLon="-122.1392167" EndLat="42.3653469" Style="Solid" Thickness="0" />
      <Element xsi:type="Line" Color="ZSEHO" StartLon="-122.1529158" StartLat="42.3803722" EndLon="-122.1493806" EndLat="42.3852331" Style="Solid" Thickness="0" />
      <Element xsi:type="Line" Color="ZSEHO" StartLon="-122.2302506" StartLat="42.3852331" EndLon="-122.2302506" EndLat="42.3600442" Style="Solid" Thickness="0" />
      <Element xsi:type="Line" Color="ZSEHO" StartLon="-122.3124464" StartLat="42.3852331" EndLon="-122.3124464" EndLat="42.3600442" Style="Solid" Thickness="0" />
      <Element xsi:type="Line" Color="ZSEHO" StartLon="-122.3349839" StartLat="42.3852331" EndLon="-122.3349839" EndLat="42.3600442" Style="Solid" Thickness="0" />
      <Element xsi:type="Line" Color="ZSEHO" StartLon="-122.2037358" StartLat="42.3852331" EndLon="-122.2143417" EndLat="42.3852331" Style="Solid" Thickness="0" />
      <Element xsi:type="Line" Color="ZSEHO" StartLon="-122.1493806" StartLat="42.3852331" EndLon="-122.1427519" EndLat="42.3852331" Style="Solid" Thickness="0" />
      <Element xsi:type="Line" Color="ZSEHO" StartLon="-122.1427519" StartLat="42.3852331" EndLon="-122.1392167" EndLat="42.3803722" Style="Solid" Thickness="0" />
      <Element xsi:type="Line" Color="ZSEHO" StartLon="-122.1865011" StartLat="42.3852331" EndLon="-122.1865011" EndLat="42.3600442" Style="Solid" Thickness="0" />
      <Element xsi:type="Line" Color="ZSEHO" StartLon="-123.2337136" StartLat="42.9456097" EndLon="-123.2301783" EndLat="42.9456097" Style="Solid" Thickness="0" />
      <Element xsi:type="Line" Color="ZSEHO" StartLon="-123.2071989" StartLat="42.9456097" EndLon="-123.2036636" EndLat="42.9482611" Style="Solid" Thickness="0" />
      <Element xsi:type="Line" Color="ZSEHO" StartLon="-123.2301783" StartLat="42.9456097" EndLon="-123.2266431" EndLat="42.9482611" Style="Solid" Thickness="0" />
      <Element xsi:type="Line" Color="ZSEHO" StartLon="-123.3331442" StartLat="42.9456097" EndLon="-123.3296089" EndLat="42.9482611" Style="Solid" Thickness="0" />
      <Element xsi:type="Line" Color="ZSEHO" StartLon="-123.3402147" StartLat="42.9456097" EndLon="-123.3331442" EndLat="42.9456097" Style="Solid" Thickness="0" />
      <Element xsi:type="Line" Color="ZSEHO" StartLon="-123.2142694" StartLat="42.9456097" EndLon="-123.2071989" EndLat="42.9456097" Style="Solid" Thickness="0" />
      <Element xsi:type="Line" Color="ZSEHO" StartLon="-123.1444472" StartLat="42.9456097" EndLon="-123.1409119" EndLat="42.9482611" Style="Solid" Thickness="0" />
      <Element xsi:type="Line" Color="ZSEHO" StartLon="-123.1515181" StartLat="42.9456097" EndLon="-123.1444472" EndLat="42.9456097" Style="Solid" Thickness="0" />
      <Element xsi:type="Line" Color="ZSEHO" StartLon="-123.1917319" StartLat="42.9456097" EndLon="-123.1917319" EndLat="42.9456097" Style="Solid" Thickness="0" />
      <Element xsi:type="Line" Color="ZSEHO" StartLon="-123.1899644" StartLat="42.9456097" EndLon="-123.1899644" EndLat="42.9482611" Style="Solid" Thickness="0" />
      <Element xsi:type="Line" Color="ZSEHO" StartLon="-123.1917319" StartLat="42.9456097" EndLon="-123.1899644" EndLat="42.9456097" Style="Solid" Thickness="0" />
      <Element xsi:type="Line" Color="ZSEHO" StartLon="-123.2372492" StartLat="42.9482611" EndLon="-123.2337136" EndLat="42.9456097" Style="Solid" Thickness="0" />
      <Element xsi:type="Line" Color="ZSEHO" StartLon="-123.2036636" StartLat="42.9482611" EndLon="-123.2036636" EndLat="42.9606347" Style="Solid" Thickness="0" />
      <Element xsi:type="Line" Color="ZSEHO" StartLon="-123.2266431" StartLat="42.9482611" EndLon="-123.2248756" EndLat="42.9509128" Style="Solid" Thickness="0" />
      <Element xsi:type="Line" Color="ZSEHO" StartLon="-123.3296089" StartLat="42.9482611" EndLon="-123.3296089" EndLat="42.9606347" Style="Solid" Thickness="0" />
      <Element xsi:type="Line" Color="ZSEHO" StartLon="-123.34375" StartLat="42.9482611" EndLon="-123.3402147" EndLat="42.9456097" Style="Solid" Thickness="0" />
      <Element xsi:type="Line" Color="ZSEHO" StartLon="-123.1409119" StartLat="42.9482611" EndLon="-123.1409119" EndLat="42.9606347" Style="Solid" Thickness="0" />
      <Element xsi:type="Line" Color="ZSEHO" StartLon="-123.1546114" StartLat="42.9482611" EndLon="-123.1515181" EndLat="42.9456097" Style="Solid" Thickness="0" />
      <Element xsi:type="Line" Color="ZSEHO" StartLon="-123.1899644" StartLat="42.9482611" EndLon="-123.1917319" EndLat="42.9482611" Style="Solid" Thickness="0" />
      <Element xsi:type="Line" Color="ZSEHO" StartLon="-123.2178047" StartLat="42.9482611" EndLon="-123.2142694" EndLat="42.9456097" Style="Solid" Thickness="0" />
      <Element xsi:type="Line" Color="ZSEHO" StartLon="-123.1917319" StartLat="42.9482611" EndLon="-123.1917319" EndLat="42.9456097" Style="Solid" Thickness="0" />
      <Element xsi:type="Line" Color="ZSEHO" StartLon="-123.2248756" StartLat="42.9509128" EndLon="-123.2248756" EndLat="42.9557739" Style="Solid" Thickness="0" />
      <Element xsi:type="Line" Color="ZSEHO" StartLon="-123.2390167" StartLat="42.9509128" EndLon="-123.2372492" EndLat="42.9482611" Style="Solid" Thickness="0" />
      <Element xsi:type="Line" Color="ZSEHO" StartLon="-123.2893947" StartLat="42.9557739" EndLon="-123.3000006" EndLat="42.9557739" Style="Solid" Thickness="0" />
      <Element xsi:type="Line" Color="ZSEHO" StartLon="-123.2248756" StartLat="42.9557739" EndLon="-123.2266431" EndLat="42.9584253" Style="Solid" Thickness="0" />
      <Element xsi:type="Line" Color="ZSEHO" StartLon="-123.2266431" StartLat="42.9584253" EndLon="-123.2301783" EndLat="42.9606347" Style="Solid" Thickness="0" />
      <Element xsi:type="Line" Color="ZSEHO" StartLon="-123.34375" StartLat="42.9584253" EndLon="-123.34375" EndLat="42.9707989" Style="Solid" Thickness="0" />
      <Element xsi:type="Line" Color="ZSEHO" StartLon="-123.1546114" StartLat="42.9584253" EndLon="-123.1546114" EndLat="42.9707989" Style="Solid" Thickness="0" />
      <Element xsi:type="Line" Color="ZSEHO" StartLon="-123.2178047" StartLat="42.9584253" EndLon="-123.2178047" EndLat="42.9707989" Style="Solid" Thickness="0" />
      <Element xsi:type="Line" Color="ZSEHO" StartLon="-123.2337136" StartLat="42.9606347" EndLon="-123.2266431" EndLat="42.9707989" Style="Solid" Thickness="0" />
      <Element xsi:type="Line" Color="ZSEHO" StartLon="-123.2301783" StartLat="42.9606347" EndLon="-123.2337136" EndLat="42.9606347" Style="Solid" Thickness="0" />
      <Element xsi:type="Line" Color="ZSEHO" StartLon="-123.3296089" StartLat="42.9606347" EndLon="-123.3331442" EndLat="42.9606347" Style="Solid" Thickness="0" />
      <Element xsi:type="Line" Color="ZSEHO" StartLon="-123.3402147" StartLat="42.9606347" EndLon="-123.34375" EndLat="42.9584253" Style="Solid" Thickness="0" />
      <Element xsi:type="Line" Color="ZSEHO" StartLon="-123.3331442" StartLat="42.9606347" EndLon="-123.3402147" EndLat="42.9606347" Style="Solid" Thickness="0" />
      <Element xsi:type="Line" Color="ZSEHO" StartLon="-123.2142694" StartLat="42.9606347" EndLon="-123.2178047" EndLat="42.9584253" Style="Solid" Thickness="0" />
      <Element xsi:type="Line" Color="ZSEHO" StartLon="-123.1444472" StartLat="42.9606347" EndLon="-123.1515181" EndLat="42.9606347" Style="Solid" Thickness="0" />
      <Element xsi:type="Line" Color="ZSEHO" StartLon="-123.1409119" StartLat="42.9606347" EndLon="-123.1444472" EndLat="42.9606347" Style="Solid" Thickness="0" />
      <Element xsi:type="Line" Color="ZSEHO" StartLon="-123.1515181" StartLat="42.9606347" EndLon="-123.1546114" EndLat="42.9584253" Style="Solid" Thickness="0" />
      <Element xsi:type="Line" Color="ZSEHO" StartLon="-123.2071989" StartLat="42.9606347" EndLon="-123.2142694" EndLat="42.9606347" Style="Solid" Thickness="0" />
      <Element xsi:type="Line" Color="ZSEHO" StartLon="-123.2036636" StartLat="42.9606347" EndLon="-123.2071989" EndLat="42.9606347" Style="Solid" Thickness="0" />
      <Element xsi:type="Line" Color="ZSEHO" StartLon="-123.3631942" StartLat="42.9632864" EndLon="-123.3578914" EndLat="42.9707989" Style="Solid" Thickness="0" />
      <Element xsi:type="Line" Color="ZSEHO" StartLon="-123.2580189" StartLat="42.9632864" EndLon="-123.2527161" EndLat="42.9707989" Style="Solid" Thickness="0" />
      <Element xsi:type="Line" Color="ZSEHO" StartLon="-123.1740556" StartLat="42.9632864" EndLon="-123.1687525" EndLat="42.9707989" Style="Solid" Thickness="0" />
      <Element xsi:type="Line" Color="ZSEHO" StartLon="-123.2527161" StartLat="42.9707989" EndLon="-123.2527161" EndLat="42.9456097" Style="Solid" Thickness="0" />
      <Element xsi:type="Line" Color="ZSEHO" StartLon="-123.34375" StartLat="42.9707989" EndLon="-123.3296089" EndLat="42.9707989" Style="Solid" Thickness="0" />
      <Element xsi:type="Line" Color="ZSEHO" StartLon="-123.3578914" StartLat="42.9707989" EndLon="-123.3578914" EndLat="42.9456097" Style="Solid" Thickness="0" />
      <Element xsi:type="Line" Color="ZSEHO" StartLon="-123.2266431" StartLat="42.9707989" EndLon="-123.2372492" EndLat="42.9707989" Style="Solid" Thickness="0" />
      <Element xsi:type="Line" Color="ZSEHO" StartLon="-123.1546114" StartLat="42.9707989" EndLon="-123.1409119" EndLat="42.9707989" Style="Solid" Thickness="0" />
      <Element xsi:type="Line" Color="ZSEHO" StartLon="-123.1687525" StartLat="42.9707989" EndLon="-123.1687525" EndLat="42.9456097" Style="Solid" Thickness="0" />
      <Element xsi:type="Line" Color="ZSEHO" StartLon="-123.2178047" StartLat="42.9707989" EndLon="-123.2036636" EndLat="42.9707989" Style="Solid" Thickness="0" />
      <Element xsi:type="Line" Color="ZSEHO" StartLon="-122.9666667" StartLat="43.4666667" EndLon="-123.3867986" EndLat="43.5732992" Style="Solid" Thickness="0" />
      <Element xsi:type="Line" Color="ZSEHO" StartLon="-122.55" StartLat="43.4666667" EndLon="-122.9666667" EndLat="43.4666667" Style="Solid" Thickness="0" />
      <Element xsi:type="Line" Color="ZSEHO" StartLon="-122.7839517" StartLat="43.5583572" EndLon="-122.7768811" EndLat="43.5583572" Style="Solid" Thickness="0" />
      <Element xsi:type="Line" Color="ZSEHO" StartLon="-122.6823117" StartLat="43.5583572" EndLon="-122.6823117" EndLat="43.5632183" Style="Solid" Thickness="0" />
      <Element xsi:type="Line" Color="ZSEHO" StartLon="-122.6681703" StartLat="43.5583572" EndLon="-122.6823117" EndLat="43.5583572" Style="Solid" Thickness="0" />
      <Element xsi:type="Line" Color="ZSEHO" StartLon="-122.7994186" StartLat="43.5583572" EndLon="-122.7958833" EndLat="43.5605669" Style="Solid" Thickness="0" />
      <Element xsi:type="Line" Color="ZSEHO" StartLon="-122.8029539" StartLat="43.5583572" EndLon="-122.7994186" EndLat="43.5583572" Style="Solid" Thickness="0" />
      <Element xsi:type="Line" Color="ZSEHO" StartLon="-122.7768811" StartLat="43.5583572" EndLon="-122.7733456" EndLat="43.5632183" Style="Solid" Thickness="0" />
      <Element xsi:type="Line" Color="ZSEHO" StartLon="-122.6509358" StartLat="43.5583572" EndLon="-122.6474006" EndLat="43.5605669" Style="Solid" Thickness="0" />
      <Element xsi:type="Line" Color="ZSEHO" StartLon="-122.6350269" StartLat="43.5583572" EndLon="-122.6350269" EndLat="43.5583572" Style="Solid" Thickness="0" />
      <Element xsi:type="Line" Color="ZSEHO" StartLon="-122.6089542" StartLat="43.5583572" EndLon="-122.6054186" EndLat="43.5632183" Style="Solid" Thickness="0" />
      <Element xsi:type="Line" Color="ZSEHO" StartLon="-122.6160247" StartLat="43.5583572" EndLon="-122.6089542" EndLat="43.5583572" Style="Solid" Thickness="0" />
      <Element xsi:type="Line" Color="ZSEHO" StartLon="-122.6580064" StartLat="43.5583572" EndLon="-122.6509358" EndLat="43.5583572" Style="Solid" Thickness="0" />
      <Element xsi:type="Line" Color="ZSEHO" StartLon="-122.6332592" StartLat="43.5583572" EndLon="-122.6332592" EndLat="43.5605669" Style="Solid" Thickness="0" />
      <Element xsi:type="Line" Color="ZSEHO" StartLon="-122.6350269" StartLat="43.5583572" EndLon="-122.6332592" EndLat="43.5583572" Style="Solid" Thickness="0" />
      <Element xsi:type="Line" Color="ZSEHO" StartLon="-122.8064892" StartLat="43.5605669" EndLon="-122.8064892" EndLat="43.5605669" Style="Solid" Thickness="0" />
      <Element xsi:type="Line" Color="ZSEHO" StartLon="-122.8064892" StartLat="43.5605669" EndLon="-122.8029539" EndLat="43.5583572" Style="Solid" Thickness="0" />
      <Element xsi:type="Line" Color="ZSEHO" StartLon="-122.7958833" StartLat="43.5605669" EndLon="-122.7941156" EndLat="43.5658697" Style="Solid" Thickness="0" />
      <Element xsi:type="Line" Color="ZSEHO" StartLon="-122.6474006" StartLat="43.5605669" EndLon="-122.6474006" EndLat="43.5733822" Style="Solid" Thickness="0" />
      <Element xsi:type="Line" Color="ZSEHO" StartLon="-122.6332592" StartLat="43.5605669" EndLon="-122.6350269" EndLat="43.5605669" Style="Solid" Thickness="0" />
      <Element xsi:type="Line" Color="ZSEHO" StartLon="-122.6350269" StartLat="43.5605669" EndLon="-122.6350269" EndLat="43.5583572" Style="Solid" Thickness="0" />
      <Element xsi:type="Line" Color="ZSEHO" StartLon="-122.6610997" StartLat="43.5605669" EndLon="-122.6580064" EndLat="43.5583572" Style="Solid" Thickness="0" />
      <Element xsi:type="Line" Color="ZSEHO" StartLon="-122.787045" StartLat="43.5632183" EndLon="-122.7839517" EndLat="43.5583572" Style="Solid" Thickness="0" />
      <Element xsi:type="Line" Color="ZSEHO" StartLon="-122.7733456" StartLat="43.5632183" EndLon="-122.7733456" EndLat="43.5680794" Style="Solid" Thickness="0" />
      <Element xsi:type="Line" Color="ZSEHO" StartLon="-122.6823117" StartLat="43.5632183" EndLon="-122.6681703" EndLat="43.5755919" Style="Solid" Thickness="0" />
      <Element xsi:type="Line" Color="ZSEHO" StartLon="-122.6191181" StartLat="43.5632183" EndLon="-122.6160247" EndLat="43.5583572" Style="Solid" Thickness="0" />
      <Element xsi:type="Line" Color="ZSEHO" StartLon="-122.6054186" StartLat="43.5632183" EndLon="-122.6054186" EndLat="43.5658697" Style="Solid" Thickness="0" />
      <Element xsi:type="Line" Color="ZSEHO" StartLon="-122.7941156" StartLat="43.5658697" EndLon="-122.7941156" EndLat="43.5755919" Style="Solid" Thickness="0" />
      <Element xsi:type="Line" Color="ZSEHO" StartLon="-122.8082569" StartLat="43.5658697" EndLon="-122.8064892" EndLat="43.5605669" Style="Solid" Thickness="0" />
      <Element xsi:type="Line" Color="ZSEHO" StartLon="-122.6191181" StartLat="43.5658697" EndLon="-122.6191181" EndLat="43.5632183" Style="Solid" Thickness="0" />
      <Element xsi:type="Line" Color="ZSEHO" StartLon="-122.6054186" StartLat="43.5658697" EndLon="-122.6107217" EndLat="43.5707308" Style="Solid" Thickness="0" />
      <Element xsi:type="Line" Color="ZSEHO" StartLon="-122.7733456" StartLat="43.5680794" EndLon="-122.7768811" EndLat="43.5733822" Style="Solid" Thickness="0" />
      <Element xsi:type="Line" Color="ZSEHO" StartLon="-122.7331317" StartLat="43.5680794" EndLon="-122.7437375" EndLat="43.5680794" Style="Solid" Thickness="0" />
      <Element xsi:type="Line" Color="ZSEHO" StartLon="-122.6107217" StartLat="43.5707308" EndLon="-122.6142569" EndLat="43.5707308" Style="Solid" Thickness="0" />
      <Element xsi:type="Line" Color="ZSEHO" StartLon="-122.6610997" StartLat="43.5707308" EndLon="-122.6610997" EndLat="43.5831044" Style="Solid" Thickness="0" />
      <Element xsi:type="Line" Color="ZSEHO" StartLon="-122.6107217" StartLat="43.5707308" EndLon="-122.6054186" EndLat="43.5755919" Style="Solid" Thickness="0" />
      <Element xsi:type="Line" Color="ZSEHO" StartLon="-122.6142569" StartLat="43.5707308" EndLon="-122.6191181" EndLat="43.5658697" Style="Solid" Thickness="0" />
      <Element xsi:type="Line" Color="ZSEHO" StartLon="-122.7768811" StartLat="43.5733822" EndLon="-122.7839517" EndLat="43.5733822" Style="Solid" Thickness="0" />
      <Element xsi:type="Line" Color="ZSEHO" StartLon="-122.7839517" StartLat="43.5733822" EndLon="-122.787045" EndLat="43.5680794" Style="Solid" Thickness="0" />
      <Element xsi:type="Line" Color="ZSEHO" StartLon="-122.6580064" StartLat="43.5733822" EndLon="-122.6610997" EndLat="43.5707308" Style="Solid" Thickness="0" />
      <Element xsi:type="Line" Color="ZSEHO" StartLon="-122.6474006" StartLat="43.5733822" EndLon="-122.6509358" EndLat="43.5733822" Style="Solid" Thickness="0" />
      <Element xsi:type="Line" Color="ZSEHO" StartLon="-122.6509358" StartLat="43.5733822" EndLon="-122.6580064" EndLat="43.5733822" Style="Solid" Thickness="0" />
      <Element xsi:type="Line" Color="ZSEHO" StartLon="-122.7017558" StartLat="43.5755919" EndLon="-122.6964528" EndLat="43.5831044" Style="Solid" Thickness="0" />
      <Element xsi:type="Line" Color="ZSEHO" StartLon="-122.7941156" StartLat="43.5755919" EndLon="-122.7958833" EndLat="43.5808947" Style="Solid" Thickness="0" />
      <Element xsi:type="Line" Color="ZSEHO" StartLon="-122.8082569" StartLat="43.5755919" EndLon="-122.8082569" EndLat="43.5658697" Style="Solid" Thickness="0" />
      <Element xsi:type="Line" Color="ZSEHO" StartLon="-122.6054186" StartLat="43.5755919" EndLon="-122.6054186" EndLat="43.5782433" Style="Solid" Thickness="0" />
      <Element xsi:type="Line" Color="ZSEHO" StartLon="-122.6191181" StartLat="43.5755919" EndLon="-122.6142569" EndLat="43.5707308" Style="Solid" Thickness="0" />
      <Element xsi:type="Line" Color="ZSEHO" StartLon="-122.6681703" StartLat="43.5755919" EndLon="-122.6681703" EndLat="43.5808947" Style="Solid" Thickness="0" />
      <Element xsi:type="Line" Color="ZSEHO" StartLon="-122.787045" StartLat="43.5782433" EndLon="-122.787045" EndLat="43.5632183" Style="Solid" Thickness="0" />
      <Element xsi:type="Line" Color="ZSEHO" StartLon="-122.6191181" StartLat="43.5782433" EndLon="-122.6191181" EndLat="43.5755919" Style="Solid" Thickness="0" />
      <Element xsi:type="Line" Color="ZSEHO" StartLon="-122.6054186" StartLat="43.5782433" EndLon="-122.6089542" EndLat="43.5831044" Style="Solid" Thickness="0" />
      <Element xsi:type="Line" Color="ZSEHO" StartLon="-122.7958833" StartLat="43.5808947" EndLon="-122.7994186" EndLat="43.5831044" Style="Solid" Thickness="0" />
      <Element xsi:type="Line" Color="ZSEHO" StartLon="-122.8064892" StartLat="43.5808947" EndLon="-122.8082569" EndLat="43.5755919" Style="Solid" Thickness="0" />
      <Element xsi:type="Line" Color="ZSEHO" StartLon="-122.6681703" StartLat="43.5808947" EndLon="-122.6717058" EndLat="43.5831044" Style="Solid" Thickness="0" />
      <Element xsi:type="Line" Color="ZSEHO" StartLon="-122.7733456" StartLat="43.5808947" EndLon="-122.7768811" EndLat="43.5831044" Style="Solid" Thickness="0" />
      <Element xsi:type="Line" Color="ZSEHO" StartLon="-122.7768811" StartLat="43.5831044" EndLon="-122.7839517" EndLat="43.5831044" Style="Solid" Thickness="0" />
      <Element xsi:type="Line" Color="ZSEHO" StartLon="-122.6964528" StartLat="43.5831044" EndLon="-122.6964528" EndLat="43.5583572" Style="Solid" Thickness="0" />
      <Element xsi:type="Line" Color="ZSEHO" StartLon="-122.7839517" StartLat="43.5831044" EndLon="-122.787045" EndLat="43.5782433" Style="Solid" Thickness="0" />
      <Element xsi:type="Line" Color="ZSEHO" StartLon="-122.8029539" StartLat="43.5831044" EndLon="-122.8064892" EndLat="43.5808947" Style="Solid" Thickness="0" />
      <Element xsi:type="Line" Color="ZSEHO" StartLon="-122.7994186" StartLat="43.5831044" EndLon="-122.8029539" EndLat="43.5831044" Style="Solid" Thickness="0" />
      <Element xsi:type="Line" Color="ZSEHO" StartLon="-122.6160247" StartLat="43.5831044" EndLon="-122.6191181" EndLat="43.5782433" Style="Solid" Thickness="0" />
      <Element xsi:type="Line" Color="ZSEHO" StartLon="-122.6089542" StartLat="43.5831044" EndLon="-122.6160247" EndLat="43.5831044" Style="Solid" Thickness="0" />
      <Element xsi:type="Line" Color="ZSEHO" StartLon="-122.6610997" StartLat="43.5831044" EndLon="-122.6474006" EndLat="43.5831044" Style="Solid" Thickness="0" />
      <Element xsi:type="Line" Color="ZSEHO" StartLon="-122.6787764" StartLat="43.5831044" EndLon="-122.6823117" EndLat="43.5808947" Style="Solid" Thickness="0" />
      <Element xsi:type="Line" Color="ZSEHO" StartLon="-122.6717058" StartLat="43.5831044" EndLon="-122.6787764" EndLat="43.5831044" Style="Solid" Thickness="0" />
      <Element xsi:type="Line" Color="ZSEHO" StartLon="-122.2195006" StartLat="43.6606556" EndLon="-122.55" EndLat="43.4666667" Style="Solid" Thickness="0" />
    </Elements>
  </VideoMap>
