<?xml version="1.0"?>
<Facility xmlns:xsi="http://www.w3.org/2001/XMLSchema-instance" xmlns:xsd="http://www.w3.org/2001/XMLSchema" ID="KPSC" Name="Tri-Cities" UpdatedOn="2021-02-26T14:31:22.3862047-08:00">
  <Frequency>25650</Frequency>
  <InformationDisplaySystemEndpoint>https://ids.zseartcc.org/remote/atis</InformationDisplaySystemEndpoint>
  <MetarObservation ObservationTimeValue="0" Enable="false" />
  <MagneticVariation MagneticVariationValue="20" Option="Subtract" />
  <Contractions />
  <Profiles>
    <Profile Name="21 VIS">
      <AirportConditions>VIS APCHS IN USE RWYS 21R &amp; 21L. DEPTG RWYS 21R &amp; 21L. VFR ACFT SAY DRCTN OF FLT.</AirportConditions>
      <AtisTemplate>[FACILITY] ATIS INFORMATION [ATIS_CODE]. [OBS_TIME]. [FULL_WX_STRING]. [ARPT_COND] [NOTAMS]</AtisTemplate>
    </Profile>
    <Profile Name="21 ILS">
      <AirportConditions>SIMUL ILS APCHS IN USE RWY 21R. DEPTG RWYS 21R &amp; 21L.</AirportConditions>
      <AtisTemplate>[FACILITY] ATIS INFORMATION [ATIS_CODE]. [OBS_TIME]. [FULL_WX_STRING]. [ARPT_COND] [NOTAMS]</AtisTemplate>
    </Profile>
    <Profile Name="3 VIS">
      <AirportConditions>VIS APCHS IN USE RWYS 3L &amp; 3R. DEPTG RWYS 3L &amp; 3R. VFR ACFT SAY DRCTN OF FLT.</AirportConditions>
      <AtisTemplate>[FACILITY] ATIS INFORMATION [ATIS_CODE]. [OBS_TIME]. [FULL_WX_STRING]. [ARPT_COND] [NOTAMS]</AtisTemplate>
    </Profile>
    <Profile Name="3 RNAV">
      <AirportConditions>SIMUL RNAV Y RWY 3L APCHS IN USE. DEPTG RWYS 3L &amp; 3R.</AirportConditions>
      <AtisTemplate>[FACILITY] ATIS INFORMATION [ATIS_CODE]. [OBS_TIME]. [FULL_WX_STRING]. [ARPT_COND] [NOTAMS]</AtisTemplate>
    </Profile>
    <Profile Name="30 VIS">
      <AirportConditions>SIMUL VIS APCHS IN USE RWY 30. DEPTG RWY 30. VFR ACFT SAY DRCTN OF FLT.</AirportConditions>
      <AtisTemplate>[FACILITY] ATIS INFORMATION [ATIS_CODE]. [OBS_TIME]. [FULL_WX_STRING]. [ARPT_COND] [NOTAMS]</AtisTemplate>
    </Profile>
    <Profile Name="30 RNAV">
      <AirportConditions>SIMUL RNAV Y RWY 30 APCHS IN USE. DEPTG RWY 30.</AirportConditions>
      <AtisTemplate>[FACILITY] ATIS INFORMATION [ATIS_CODE]. [OBS_TIME]. [FULL_WX_STRING]. [ARPT_COND] [NOTAMS]</AtisTemplate>
    </Profile>
    <Profile Name="12 VIS">
      <AirportConditions>SIMUL VIS APCHS IN USE RWY 12. DEPTG RWY 12. VFR ACFT SAY DRCTN OF FLT.</AirportConditions>
      <AtisTemplate>[FACILITY] ATIS INFORMATION [ATIS_CODE]. [OBS_TIME]. [FULL_WX_STRING]. [ARPT_COND] [NOTAMS]</AtisTemplate>
    </Profile>
    <Profile Name="12 RNAV">
      <AirportConditions>SIMUL RNAV Y RWY 12 APCHS IN USE. DEPTG RWY 12.</AirportConditions>
      <AtisTemplate>[FACILITY] ATIS INFORMATION [ATIS_CODE]. [OBS_TIME]. [FULL_WX_STRING]. [ARPT_COND] [NOTAMS]</AtisTemplate>
    </Profile>
  </Profiles>
  <UseInternationalFormat>false</UseInternationalFormat>
  <VoiceRecordEnabled>false</VoiceRecordEnabled>
  <VoiceName>Default</VoiceName>
  <VoiceGender>Male</VoiceGender>
  <Notams />
  <AirportConditions>
    <AirportCondition Message="RNAV APCHS AVBL ON RQST." IsSelected="false" />
  </AirportConditions>
</Facility>